{
  "v": 2,
  "updated": "2026-04-08T20:34:51.479Z",
  "stations": {
    "nts1": [
      {
        "n": "HOOVERSOUND W/ SHERELLE & NAINA",
        "s": "2026-04-08T21:00:00+01:00",
        "e": "2026-04-08T22:00:00+01:00",
        "d": "Hi octane monthly missives from Naina & Sherelle, the minds behind the hybrid Jungle, Techno & Footwork label Hooversound.\nFrom the host: \"Hooversound artist celebrates his new EP on the label with a special takeover on NTS.\"",
        "j": "SHERELLE & NAINA",
        "u": "https://www.nts.live/api/v2/shows/hooversound/episodes/hooversound-8th-april-2026",
        "t": "monthly",
        "p": "hooversound",
        "ap": [
          "sherelle"
        ]
      },
      {
        "n": "Crystallmess: Unleashed",
        "s": "2026-04-08T22:00:00+01:00",
        "e": "2026-04-08T23:00:00+01:00",
        "d": "The French producer, DJ & Work In Progress 2019 alumna Crystallmess is Unleashed - bleeding edge club sounds & emotional content every month.",
        "j": "Unleashed",
        "u": "https://www.nts.live/api/v2/shows/crystallmess/episodes/crystallmess-8th-april-2026",
        "t": "monthly"
      },
      {
        "n": "SLIME FM W/ KHADIJA AL HANAFI",
        "s": "2026-04-08T23:00:00+01:00",
        "e": "2026-04-09T00:00:00+01:00",
        "d": null,
        "j": null,
        "u": null,
        "p": "slimefm"
      },
      {
        "n": "GRRL",
        "s": "2026-04-09T00:00:00+01:00",
        "e": "2026-04-09T01:00:00+01:00",
        "d": null,
        "j": null,
        "u": null,
        "t": "monthly",
        "p": "grrl"
      },
      {
        "n": "Can You Feel The Sun W/ Katiusha",
        "s": "2026-04-09T01:00:00+01:00",
        "e": "2026-04-09T02:00:00+01:00",
        "d": null,
        "j": null,
        "u": null
      },
      {
        "n": "The Lunacy of Flowers w/ Dave ID (R)",
        "s": "2026-04-09T02:00:00+01:00",
        "e": "2026-04-09T03:00:00+01:00",
        "d": null,
        "j": "Dave ID",
        "u": null,
        "t": "restream"
      },
      {
        "n": "DON'T TRIP W/ MARGARITA (R)",
        "s": "2026-04-09T03:00:00+01:00",
        "e": "2026-04-09T05:00:00+01:00",
        "d": null,
        "j": "MARGARITA",
        "u": null,
        "t": "restream"
      },
      {
        "n": "SARA A (R)",
        "s": "2026-04-09T05:00:00+01:00",
        "e": "2026-04-09T06:00:00+01:00",
        "d": null,
        "j": null,
        "u": null,
        "t": "restream",
        "p": "saraa"
      },
      {
        "n": "KRANKY (R)",
        "s": "2026-04-09T06:00:00+01:00",
        "e": "2026-04-09T07:00:00+01:00",
        "d": null,
        "j": null,
        "u": null,
        "t": "restream",
        "p": "kranky"
      },
      {
        "n": "THE EARLY BIRD SHOW W/ PAM",
        "s": "2026-04-09T07:00:00+01:00",
        "e": "2026-04-09T09:00:00+01:00",
        "d": null,
        "j": null,
        "u": null
      },
      {
        "n": "THE NTS BREAKFAST SHOW W/ FLO",
        "s": "2026-04-09T09:00:00+01:00",
        "e": "2026-04-09T11:00:00+01:00",
        "d": null,
        "j": "FLO",
        "u": null,
        "t": "regular",
        "p": "flo"
      },
      {
        "n": "SOUP TO NUTS W/ BABYSCHÖN",
        "s": "2026-04-09T11:00:00+01:00",
        "e": "2026-04-09T13:00:00+01:00",
        "d": null,
        "j": "BABYSCHÖN",
        "u": null,
        "t": "weekly"
      },
      {
        "n": "DANCE MUSIC SHOW W/ BELL TOWERS - FM lite hits",
        "s": "2026-04-09T13:00:00+01:00",
        "e": "2026-04-09T14:00:00+01:00",
        "d": null,
        "j": null,
        "u": null,
        "p": "belltowers"
      },
      {
        "n": "RHYTHM CONNECTION",
        "s": "2026-04-09T14:00:00+01:00",
        "e": "2026-04-09T16:00:00+01:00",
        "d": null,
        "j": null,
        "u": null,
        "t": "monthly"
      },
      {
        "n": "RHYTHM CONNECTION w/ Zoe Garbett",
        "s": "2026-04-09T16:00:00+01:00",
        "e": "2026-04-09T17:00:00+01:00",
        "d": null,
        "j": null,
        "u": null
      },
      {
        "n": "Chicken Foot Soup w/ Goya Gumbani and Dom P",
        "s": "2026-04-09T17:00:00+01:00",
        "e": "2026-04-09T19:00:00+01:00",
        "d": null,
        "j": "Goya Gumbani and Dom P",
        "u": null,
        "t": "monthly"
      },
      {
        "n": "A. K. PAUL  - LANDCRUISIN' 10Y AND THE DAWN OF ORGANIC SYSTEMS",
        "s": "2026-04-09T19:00:00+01:00",
        "e": "2026-04-09T20:00:00+01:00",
        "d": null,
        "j": null,
        "u": null
      },
      {
        "n": "Armand Hammer",
        "s": "2026-04-09T20:00:00+01:00",
        "e": "2026-04-09T21:00:00+01:00",
        "d": null,
        "j": null,
        "u": null,
        "p": "hammer"
      }
    ],
    "nts2": [
      {
        "n": "HEAVEN AND EARTH MAGIC W/ JOCELYN ROMO",
        "s": "2026-04-08T21:00:00+01:00",
        "e": "2026-04-08T22:00:00+01:00",
        "d": "Exploring inner and outer worlds, cosmic and pastoral sounds, and the intersection between reality and dreams once a month with Jocelyn Romo's mix of international and private press folk, instrumental guitar, dream country, ambient, new age, kosmiche, psych and beyond\nFrom the host: \"Night-blooming jasmine through an open window on a spring night.\"",
        "j": "JOCELYN ROMO",
        "u": "https://www.nts.live/api/v2/shows/jocelyn-romo/episodes/jocelyn-romo-8th-april-2026",
        "t": "monthly",
        "p": "jocelynromo"
      },
      {
        "n": "LUKE MELE",
        "s": "2026-04-08T22:00:00+01:00",
        "e": "2026-04-08T23:00:00+01:00",
        "d": "Soft-touch home listening selections live from LA every month with Luke Mele. Traversing ambient, jazz, guitar tones and more. ",
        "j": null,
        "u": "https://www.nts.live/api/v2/shows/luke-mele/episodes/luke-mele-8th-april-2026",
        "t": "monthly",
        "p": "lukemele"
      },
      {
        "n": "Beyond The Clouds w/ Masha Mar",
        "s": "2026-04-08T23:00:00+01:00",
        "e": "2026-04-09T00:00:00+01:00",
        "d": null,
        "j": null,
        "u": null,
        "p": "mashamar"
      },
      {
        "n": "THE ATHENIAN MARKETPLACE",
        "s": "2026-04-09T00:00:00+01:00",
        "e": "2026-04-09T02:00:00+01:00",
        "d": null,
        "j": null,
        "u": null
      },
      {
        "n": "COLD PIZZA W/ STUD1NT",
        "s": "2026-04-09T02:00:00+01:00",
        "e": "2026-04-09T03:00:00+01:00",
        "d": null,
        "j": null,
        "u": null,
        "p": "coldpizza"
      },
      {
        "n": "Club Aerobics w/ Bianca Oblivion & Meg10",
        "s": "2026-04-09T03:00:00+01:00",
        "e": "2026-04-09T04:00:00+01:00",
        "d": null,
        "j": null,
        "u": null,
        "p": "biancaoblivion",
        "ap": [
          "clubaerobics"
        ]
      },
      {
        "n": "System Olympia (R)",
        "s": "2026-04-09T04:00:00+01:00",
        "e": "2026-04-09T05:00:00+01:00",
        "d": null,
        "j": null,
        "u": null,
        "t": "restream",
        "p": "systemolympia"
      },
      {
        "n": "In Focus: Soo Young Park (R)",
        "s": "2026-04-09T05:00:00+01:00",
        "e": "2026-04-09T06:00:00+01:00",
        "d": null,
        "j": "Soo Young Park",
        "u": null,
        "t": "restream"
      },
      {
        "n": "LOST PSYCHEDELIA W/ EMERALD",
        "s": "2026-04-09T06:00:00+01:00",
        "e": "2026-04-09T07:00:00+01:00",
        "d": null,
        "j": null,
        "u": null,
        "p": "emerald"
      },
      {
        "n": "SOUNDS OF FIJI W/ MANA FRACTAL",
        "s": "2026-04-09T07:00:00+01:00",
        "e": "2026-04-09T08:00:00+01:00",
        "d": null,
        "j": null,
        "u": null
      },
      {
        "n": "Relief Records Mix w/ RICMAYHEM",
        "s": "2026-04-09T08:00:00+01:00",
        "e": "2026-04-09T09:00:00+01:00",
        "d": null,
        "j": null,
        "u": null
      },
      {
        "n": "LA RUTA DEL BAKALAO W/ CAFÉ RIOT",
        "s": "2026-04-09T09:00:00+01:00",
        "e": "2026-04-09T10:00:00+01:00",
        "d": null,
        "j": null,
        "u": null
      },
      {
        "n": "My Eyes Glaze Over: Mego's first phase - 1994-2005",
        "s": "2026-04-09T10:00:00+01:00",
        "e": "2026-04-09T11:00:00+01:00",
        "d": null,
        "j": null,
        "u": null
      },
      {
        "n": "Sounds on Screen: HK Crime Movies",
        "s": "2026-04-09T11:00:00+01:00",
        "e": "2026-04-09T12:00:00+01:00",
        "d": null,
        "j": "HK Crime Movies",
        "u": null,
        "t": "biweekly"
      },
      {
        "n": "On the Road w/ Adelina S - Welcome to Hamarabr Pt. 2",
        "s": "2026-04-09T12:00:00+01:00",
        "e": "2026-04-09T13:00:00+01:00",
        "d": null,
        "j": "Adelina S",
        "u": null,
        "t": "monthly"
      },
      {
        "n": "LLOYD 'MUSCLEHEAD' SAXON",
        "s": "2026-04-09T13:00:00+01:00",
        "e": "2026-04-09T14:00:00+01:00",
        "d": null,
        "j": null,
        "u": null,
        "t": "monthly"
      },
      {
        "n": "MiNaYo w/ Ruth Tafébé",
        "s": "2026-04-09T14:00:00+01:00",
        "e": "2026-04-09T15:00:00+01:00",
        "d": null,
        "j": "Ruth Tafébé",
        "u": null,
        "t": "monthly"
      },
      {
        "n": "DesiVinyl w/ Ruby Khaira",
        "s": "2026-04-09T15:00:00+01:00",
        "e": "2026-04-09T16:00:00+01:00",
        "d": null,
        "j": null,
        "u": null,
        "p": "rubykhaira"
      }
    ],
    "subtle": [
      {
        "n": "Marauder & Meg",
        "s": "2026-04-08T20:00:00Z",
        "e": "2026-04-08T22:00:00Z",
        "d": null,
        "j": null,
        "u": null,
        "t": "monthly"
      },
      {
        "n": "Psyked ",
        "s": "2026-04-08T22:00:00Z",
        "e": "2026-04-08T23:00:00Z",
        "d": null,
        "j": null,
        "u": null,
        "t": "monthly",
        "p": "psyked"
      },
      {
        "n": "WOODWORK ",
        "s": "2026-04-08T23:00:00Z",
        "e": "2026-04-09T00:00:00Z",
        "d": null,
        "j": null,
        "u": null,
        "t": "monthly"
      },
      {
        "n": "The Dubversified Show",
        "s": "2026-04-09T00:00:00Z",
        "e": "2026-04-09T02:00:00Z",
        "d": "Dubversified showcases Canadian West Coast DJ talent specializing in Bass Music. Hosted by Mirage, founder of Dubversified Culture, a community-led organization focusing on music, art, and events. Mirage, originally from Québec, blends house and hip-hop since 2010, now exploring 140bpm and Deep D&B.",
        "j": null,
        "u": null,
        "t": "monthly"
      },
      {
        "n": "rowthedecks",
        "s": "2026-04-09T02:00:00Z",
        "e": "2026-04-09T03:00:00Z",
        "d": null,
        "j": null,
        "u": null,
        "t": "monthly",
        "p": "rowthedecks"
      },
      {
        "n": "kikitza",
        "s": "2026-04-09T03:00:00Z",
        "e": "2026-04-09T04:00:00Z",
        "d": null,
        "j": null,
        "u": null,
        "t": "monthly"
      },
      {
        "n": "Making Hay w/ natdav",
        "s": "2026-04-09T07:00:00Z",
        "e": "2026-04-09T08:00:00Z",
        "d": null,
        "j": "natdav",
        "u": null,
        "t": "monthly"
      },
      {
        "n": "Deep Awake by Semaj",
        "s": "2026-04-09T08:00:00Z",
        "e": "2026-04-09T09:00:00Z",
        "d": null,
        "j": null,
        "u": null,
        "t": "monthly",
        "p": "deepawakebysemaj"
      },
      {
        "n": "Sublevel",
        "s": "2026-04-09T09:00:00Z",
        "e": "2026-04-09T11:00:00Z",
        "d": null,
        "j": null,
        "u": null
      },
      {
        "n": "Con Artist",
        "s": "2026-04-09T11:00:00Z",
        "e": "2026-04-09T12:00:00Z",
        "d": null,
        "j": null,
        "u": null,
        "t": "monthly"
      },
      {
        "n": "Into The Lion's Den w/ Restrikt",
        "s": "2026-04-09T12:00:00Z",
        "e": "2026-04-09T13:00:00Z",
        "d": null,
        "j": "Restrikt",
        "u": null,
        "t": "monthly"
      },
      {
        "n": "Marigold",
        "s": "2026-04-09T13:00:00Z",
        "e": "2026-04-09T14:00:00Z",
        "d": null,
        "j": null,
        "u": null,
        "t": "monthly"
      },
      {
        "n": "Hostile Architecture w/ ODW",
        "s": "2026-04-09T15:00:00Z",
        "e": "2026-04-09T16:00:00Z",
        "d": null,
        "j": "ODW",
        "u": null,
        "t": "monthly"
      },
      {
        "n": "Lemtom",
        "s": "2026-04-09T16:00:00Z",
        "e": "2026-04-09T17:00:00Z",
        "d": null,
        "j": null,
        "u": null,
        "p": "lemtom"
      },
      {
        "n": "Say Less",
        "s": "2026-04-09T17:00:00Z",
        "e": "2026-04-09T19:00:00Z",
        "d": null,
        "j": null,
        "u": null,
        "t": "monthly"
      },
      {
        "n": "VALENTIA",
        "s": "2026-04-09T19:00:00Z",
        "e": "2026-04-09T20:00:00Z",
        "d": null,
        "j": null,
        "u": null
      },
      {
        "n": "D-Code & Psylence",
        "s": "2026-04-09T20:00:00Z",
        "e": "2026-04-09T21:00:00Z",
        "d": null,
        "j": null,
        "u": null,
        "t": "monthly"
      },
      {
        "n": "Benteki",
        "s": "2026-04-09T21:00:00Z",
        "e": "2026-04-09T22:00:00Z",
        "d": null,
        "j": null,
        "u": null,
        "t": "monthly",
        "p": "benteki"
      },
      {
        "n": "Matt Frost ",
        "s": "2026-04-09T22:00:00Z",
        "e": "2026-04-09T23:00:00Z",
        "d": "Potent Funk records’ Matt Frost - Well known for his technical abilities and Sleazy bass music style, Frost covers all angles from UK alt Rap to the LA beat scene.",
        "j": null,
        "u": null,
        "t": "monthly",
        "p": "mattfrost"
      },
      {
        "n": " Dubstar Records Show w/ Dubfreq",
        "s": "2026-04-09T23:00:00Z",
        "e": "2026-04-10T00:00:00Z",
        "d": null,
        "j": "Dubfreq",
        "u": null,
        "t": "monthly"
      },
      {
        "n": "Insoundfromwayback",
        "s": "2026-04-10T00:00:00Z",
        "e": "2026-04-10T01:00:00Z",
        "d": null,
        "j": null,
        "u": null,
        "t": "monthly"
      },
      {
        "n": "Pete Shredz",
        "s": "2026-04-10T01:00:00Z",
        "e": "2026-04-10T02:00:00Z",
        "d": null,
        "j": null,
        "u": null,
        "t": "monthly",
        "p": "peteshredz"
      },
      {
        "n": "Macks",
        "s": "2026-04-10T02:00:00Z",
        "e": "2026-04-10T03:00:00Z",
        "d": null,
        "j": null,
        "u": null,
        "t": "monthly"
      },
      {
        "n": "Lava Recordings with 99 ranch",
        "s": "2026-04-10T03:00:00Z",
        "e": "2026-04-10T04:00:00Z",
        "d": null,
        "j": null,
        "u": null,
        "t": "monthly"
      },
      {
        "n": "Holy Crow w/ Isis Moray",
        "s": "2026-04-10T09:00:00Z",
        "e": "2026-04-10T10:00:00Z",
        "d": null,
        "j": "Isis Moray",
        "u": null,
        "t": "monthly"
      },
      {
        "n": "Tom Ferrare",
        "s": "2026-04-10T10:00:00Z",
        "e": "2026-04-10T11:00:00Z",
        "d": null,
        "j": null,
        "u": null,
        "t": "monthly"
      },
      {
        "n": "Electrolytes with Joly",
        "s": "2026-04-10T11:00:00Z",
        "e": "2026-04-10T12:00:00Z",
        "d": null,
        "j": null,
        "u": null,
        "t": "monthly",
        "p": "electrolyteswithjoly"
      },
      {
        "n": "Sauce Collective ",
        "s": "2026-04-10T13:00:00Z",
        "e": "2026-04-10T14:00:00Z",
        "d": null,
        "j": null,
        "u": null,
        "t": "monthly",
        "p": "collective"
      },
      {
        "n": "Kamzuqi",
        "s": "2026-04-10T14:00:00Z",
        "e": "2026-04-10T15:00:00Z",
        "d": null,
        "j": null,
        "u": null,
        "t": "monthly",
        "p": "kamzuqi"
      },
      {
        "n": "The Free Range Sounds Show",
        "s": "2026-04-10T15:00:00Z",
        "e": "2026-04-10T17:00:00Z",
        "d": null,
        "j": null,
        "u": null,
        "t": "monthly"
      },
      {
        "n": "SYNES",
        "s": "2026-04-10T18:00:00Z",
        "e": "2026-04-10T19:00:00Z",
        "d": null,
        "j": null,
        "u": null,
        "t": "monthly",
        "p": "synes"
      },
      {
        "n": "Pent.1",
        "s": "2026-04-10T19:00:00Z",
        "e": "2026-04-10T20:00:00Z",
        "d": null,
        "j": null,
        "u": null,
        "t": "monthly"
      },
      {
        "n": " Dorian Day b2b Dunman",
        "s": "2026-04-10T20:00:00Z",
        "e": "2026-04-10T21:00:00Z",
        "d": null,
        "j": null,
        "u": null,
        "p": "dunman"
      },
      {
        "n": "1V & Broken Boxes",
        "s": "2026-04-10T22:00:00Z",
        "e": "2026-04-10T23:00:00Z",
        "d": null,
        "j": null,
        "u": null,
        "t": "monthly"
      },
      {
        "n": "Spaghetti Junction w/ Sartana",
        "s": "2026-04-10T23:00:00Z",
        "e": "2026-04-11T00:00:00Z",
        "d": null,
        "j": "Sartana",
        "u": null,
        "t": "monthly"
      },
      {
        "n": "MANNRS",
        "s": "2026-04-11T00:00:00Z",
        "e": "2026-04-11T01:00:00Z",
        "d": null,
        "j": null,
        "u": null,
        "t": "monthly",
        "p": "mannrs"
      },
      {
        "n": "Signal Flow ",
        "s": "2026-04-11T01:00:00Z",
        "e": "2026-04-11T02:00:00Z",
        "d": null,
        "j": null,
        "u": null,
        "t": "monthly"
      },
      {
        "n": "TheComplexCurve",
        "s": "2026-04-11T02:00:00Z",
        "e": "2026-04-11T03:00:00Z",
        "d": null,
        "j": null,
        "u": null,
        "t": "monthly",
        "p": "thecomplexcurve"
      },
      {
        "n": "REFERENCES...w/ KPB",
        "s": "2026-04-11T07:00:00Z",
        "e": "2026-04-11T08:00:00Z",
        "d": null,
        "j": null,
        "u": null,
        "t": "monthly"
      },
      {
        "n": " SCOPE__EM",
        "s": "2026-04-11T09:00:00Z",
        "e": "2026-04-11T10:00:00Z",
        "d": null,
        "j": null,
        "u": null,
        "t": "monthly"
      },
      {
        "n": "Poolside Convo w/ Gabe",
        "s": "2026-04-11T10:00:00Z",
        "e": "2026-04-11T11:00:00Z",
        "d": null,
        "j": "Gabe",
        "u": null,
        "t": "monthly"
      },
      {
        "n": "Cam Christie",
        "s": "2026-04-11T11:00:00Z",
        "e": "2026-04-11T13:00:00Z",
        "d": null,
        "j": null,
        "u": null,
        "t": "monthly",
        "p": "camchristie"
      },
      {
        "n": " Morriarchi",
        "s": "2026-04-11T13:00:00Z",
        "e": "2026-04-11T14:00:00Z",
        "d": null,
        "j": null,
        "u": null,
        "t": "monthly"
      },
      {
        "n": "Charlie Kelly ",
        "s": "2026-04-11T14:00:00Z",
        "e": "2026-04-11T15:00:00Z",
        "d": "Get ready to embark on a captivating sonic journey of underground music with Charlie Kelly. Including new and timeless sounds from the depths of rap, drill, grime, and experimental genres from the vibrant streets of the UK and beyond. Charlie unearths the very best in music that pushes boundaries. Off the mic, Charlie is a Radio Producer and Social Media Executive with an eclectic music taste spanning across many different cultures, decades, and styles. Hailing from North London with a love for audio and pop culture, you can expect to hear tune after tune when you’re locked into Charlie Kelly on Subtle.",
        "j": null,
        "u": null,
        "t": "monthly"
      },
      {
        "n": "Niamh",
        "s": "2026-04-11T15:00:00Z",
        "e": "2026-04-11T16:00:00Z",
        "d": null,
        "j": null,
        "u": null,
        "p": "niamh"
      },
      {
        "n": "BirdE",
        "s": "2026-04-11T16:00:00Z",
        "e": "2026-04-11T17:00:00Z",
        "d": "BirdE brings an hour of the freshest Drum and Bass covering everything from liquid to techy steppers - the deeper the better.",
        "j": null,
        "u": null,
        "t": "monthly"
      },
      {
        "n": "Counter Culture",
        "s": "2026-04-11T17:00:00Z",
        "e": "2026-04-11T18:00:00Z",
        "d": "Originally from Cambridge, Counter Culture's selection deftly navigates across a myriad of influences and exclusives from himself & friends.\r\nExpect some of the freshest rolling soul straight to your headspace.",
        "j": null,
        "u": null,
        "t": "monthly",
        "p": "counterculture"
      },
      {
        "n": "Strictly Business Show w/ Qua Rush & Flipz MC",
        "s": "2026-04-11T18:00:00Z",
        "e": "2026-04-11T19:00:00Z",
        "d": null,
        "j": "Qua Rush & Flipz MC",
        "u": null,
        "t": "monthly"
      },
      {
        "n": "Kimber & Kid Kun",
        "s": "2026-04-11T19:00:00Z",
        "e": "2026-04-11T21:00:00Z",
        "d": null,
        "j": null,
        "u": null,
        "t": "monthly"
      },
      {
        "n": "BRINK",
        "s": "2026-04-11T21:00:00Z",
        "e": "2026-04-11T22:00:00Z",
        "d": null,
        "j": null,
        "u": null,
        "t": "monthly"
      },
      {
        "n": "Katarina",
        "s": "2026-04-11T22:00:00Z",
        "e": "2026-04-11T23:00:00Z",
        "d": null,
        "j": null,
        "u": null,
        "t": "monthly",
        "p": "katarina"
      },
      {
        "n": " Swing Thing w/ Oka",
        "s": "2026-04-11T23:00:00Z",
        "e": "2026-04-12T00:00:00Z",
        "d": null,
        "j": null,
        "u": null
      },
      {
        "n": "Concrete Law - Pharma&Sedan",
        "s": "2026-04-12T00:00:00Z",
        "e": "2026-04-12T01:00:00Z",
        "d": null,
        "j": "Pharma&Sedan",
        "u": null,
        "t": "monthly"
      },
      {
        "n": "Dubwise & Beyond w/ 8BallPosse",
        "s": "2026-04-12T01:00:00Z",
        "e": "2026-04-12T02:00:00Z",
        "d": null,
        "j": "8BallPosse",
        "u": null,
        "t": "monthly"
      },
      {
        "n": "Etno Selects",
        "s": "2026-04-12T02:00:00Z",
        "e": "2026-04-12T03:00:00Z",
        "d": null,
        "j": null,
        "u": null,
        "t": "monthly",
        "p": "etnoselects"
      },
      {
        "n": "RWND140",
        "s": "2026-04-12T03:00:00Z",
        "e": "2026-04-12T05:00:00Z",
        "d": null,
        "j": null,
        "u": null,
        "t": "monthly"
      },
      {
        "n": "Kiki B",
        "s": "2026-04-12T06:00:00Z",
        "e": "2026-04-12T07:00:00Z",
        "d": null,
        "j": null,
        "u": null,
        "t": "monthly",
        "p": "kikib"
      },
      {
        "n": "Kakuna",
        "s": "2026-04-12T08:00:00Z",
        "e": "2026-04-12T09:00:00Z",
        "d": null,
        "j": null,
        "u": null,
        "t": "monthly",
        "p": "kakuna"
      },
      {
        "n": "Agony Plants",
        "s": "2026-04-12T09:00:00Z",
        "e": "2026-04-12T10:00:00Z",
        "d": null,
        "j": null,
        "u": null,
        "t": "monthly",
        "p": "agonyplants"
      },
      {
        "n": "Chameleon: Liminal Bleeps",
        "s": "2026-04-12T10:00:00Z",
        "e": "2026-04-12T11:00:00Z",
        "d": null,
        "j": "Liminal Bleeps",
        "u": null,
        "t": "monthly"
      },
      {
        "n": "COPYPASTE w/ KLS.RDR ",
        "s": "2026-04-12T11:00:00Z",
        "e": "2026-04-12T12:00:00Z",
        "d": null,
        "j": "KLS.RDR",
        "u": null,
        "t": "monthly"
      },
      {
        "n": "5 Decades of Dub w/ Joe Vincent",
        "s": "2026-04-12T12:00:00Z",
        "e": "2026-04-12T13:00:00Z",
        "d": null,
        "j": "Joe Vincent",
        "u": null,
        "t": "monthly"
      },
      {
        "n": "Comfy Bella",
        "s": "2026-04-12T13:00:00Z",
        "e": "2026-04-12T14:00:00Z",
        "d": null,
        "j": null,
        "u": null,
        "t": "monthly"
      },
      {
        "n": " Alien Izz",
        "s": "2026-04-12T14:00:00Z",
        "e": "2026-04-12T15:00:00Z",
        "d": null,
        "j": null,
        "u": null,
        "t": "monthly",
        "p": "alienizz"
      },
      {
        "n": "The Garage Garden",
        "s": "2026-04-12T15:00:00Z",
        "e": "2026-04-12T16:00:00Z",
        "d": null,
        "j": null,
        "u": null,
        "t": "monthly",
        "p": "garagegarden"
      },
      {
        "n": " NULLIFY",
        "s": "2026-04-12T16:00:00Z",
        "e": "2026-04-12T17:00:00Z",
        "d": null,
        "j": null,
        "u": null,
        "t": "monthly",
        "p": "nullify"
      },
      {
        "n": "Marchborn",
        "s": "2026-04-12T17:00:00Z",
        "e": "2026-04-12T18:00:00Z",
        "d": null,
        "j": null,
        "u": null,
        "t": "monthly"
      },
      {
        "n": "Break Check",
        "s": "2026-04-12T18:00:00Z",
        "e": "2026-04-12T19:00:00Z",
        "d": null,
        "j": null,
        "u": null,
        "t": "monthly",
        "p": "breakcheck"
      },
      {
        "n": "FKOF",
        "s": "2026-04-12T19:00:00Z",
        "e": "2026-04-12T21:00:00Z",
        "d": null,
        "j": null,
        "u": null,
        "t": "monthly",
        "p": "fkof"
      },
      {
        "n": " Ms. Renegade",
        "s": "2026-04-12T21:00:00Z",
        "e": "2026-04-12T22:00:00Z",
        "d": null,
        "j": null,
        "u": null,
        "t": "monthly"
      },
      {
        "n": "Eva de Ree",
        "s": "2026-04-12T22:00:00Z",
        "e": "2026-04-12T23:00:00Z",
        "d": null,
        "j": null,
        "u": null
      },
      {
        "n": "DJ OJ",
        "s": "2026-04-12T23:00:00Z",
        "e": "2026-04-13T00:00:00Z",
        "d": null,
        "j": null,
        "u": null,
        "t": "monthly",
        "p": "djoj"
      },
      {
        "n": "CYBER1A",
        "s": "2026-04-13T00:00:00Z",
        "e": "2026-04-13T01:00:00Z",
        "d": null,
        "j": null,
        "u": null,
        "t": "monthly",
        "p": "cyber1a"
      },
      {
        "n": "Hikayat Bassita",
        "s": "2026-04-13T01:00:00Z",
        "e": "2026-04-13T02:00:00Z",
        "d": null,
        "j": null,
        "u": null,
        "t": "monthly",
        "p": "hikayatbassita"
      },
      {
        "n": "Izzla",
        "s": "2026-04-13T02:00:00Z",
        "e": "2026-04-13T03:00:00Z",
        "d": null,
        "j": null,
        "u": null
      },
      {
        "n": "5p3c141",
        "s": "2026-04-13T04:00:00Z",
        "e": "2026-04-13T05:00:00Z",
        "d": null,
        "j": null,
        "u": null,
        "t": "monthly",
        "p": "5p3c141"
      },
      {
        "n": " Tribalismo",
        "s": "2026-04-13T08:00:00Z",
        "e": "2026-04-13T09:00:00Z",
        "d": null,
        "j": null,
        "u": null,
        "t": "monthly",
        "p": "tribalismo"
      },
      {
        "n": "syncop8",
        "s": "2026-04-13T10:00:00Z",
        "e": "2026-04-13T11:00:00Z",
        "d": "ixxi and Fei take you on a percussive journey with their show syncop8, moving from downtempo ambient to breaks, polyrhythms, and high energy beats, exploring every rhythmic and textural nuance in between.",
        "j": null,
        "u": null,
        "t": "monthly"
      },
      {
        "n": "lot five two",
        "s": "2026-04-13T11:00:00Z",
        "e": "2026-04-13T12:00:00Z",
        "d": null,
        "j": null,
        "u": null,
        "t": "monthly",
        "p": "lotfivetwo"
      },
      {
        "n": "Bittersweet Sounds w/ Mass Hysteria",
        "s": "2026-04-13T12:00:00Z",
        "e": "2026-04-13T13:00:00Z",
        "d": null,
        "j": "Mass Hysteria",
        "u": null,
        "t": "monthly"
      },
      {
        "n": "Louis Selwyn",
        "s": "2026-04-13T13:00:00Z",
        "e": "2026-04-13T15:00:00Z",
        "d": null,
        "j": null,
        "u": null,
        "t": "monthly",
        "p": "louisselwyn"
      },
      {
        "n": "UWOT",
        "s": "2026-04-13T15:00:00Z",
        "e": "2026-04-13T16:00:00Z",
        "d": null,
        "j": null,
        "u": null,
        "t": "monthly",
        "p": "uwot"
      },
      {
        "n": "PADWICK",
        "s": "2026-04-13T16:00:00Z",
        "e": "2026-04-13T18:00:00Z",
        "d": "Representing UK Bass Music Culture across a range of styles, sounds and tempos.",
        "j": null,
        "u": null,
        "t": "monthly"
      },
      {
        "n": "C Frame",
        "s": "2026-04-13T18:00:00Z",
        "e": "2026-04-13T19:00:00Z",
        "d": null,
        "j": null,
        "u": null,
        "t": "monthly"
      },
      {
        "n": "Elrobo's Selectas",
        "s": "2026-04-13T19:00:00Z",
        "e": "2026-04-13T20:00:00Z",
        "d": null,
        "j": null,
        "u": null,
        "t": "monthly"
      },
      {
        "n": "Zubz Dubz",
        "s": "2026-04-13T20:00:00Z",
        "e": "2026-04-13T21:00:00Z",
        "d": null,
        "j": null,
        "u": null,
        "t": "monthly",
        "p": "zubzdubz"
      },
      {
        "n": " Subtext w/ Preet",
        "s": "2026-04-13T21:00:00Z",
        "e": "2026-04-13T22:00:00Z",
        "d": null,
        "j": "Preet",
        "u": null,
        "t": "monthly"
      },
      {
        "n": "Factory Floor ",
        "s": "2026-04-13T22:00:00Z",
        "e": "2026-04-13T23:00:00Z",
        "d": null,
        "j": null,
        "u": null,
        "t": "monthly"
      },
      {
        "n": "Yung Dave",
        "s": "2026-04-13T23:00:00Z",
        "e": "2026-04-14T00:00:00Z",
        "d": null,
        "j": null,
        "u": null,
        "t": "monthly",
        "p": "yungdave"
      },
      {
        "n": "Skee Sunday",
        "s": "2026-04-14T00:00:00Z",
        "e": "2026-04-14T01:00:00Z",
        "d": null,
        "j": null,
        "u": null,
        "t": "monthly",
        "p": "skeesunday"
      },
      {
        "n": "dbeater",
        "s": "2026-04-14T01:00:00Z",
        "e": "2026-04-14T02:00:00Z",
        "d": null,
        "j": null,
        "u": null,
        "t": "monthly",
        "p": "dbeater"
      },
      {
        "n": "Ethereal DJ",
        "s": "2026-04-14T02:00:00Z",
        "e": "2026-04-14T03:00:00Z",
        "d": null,
        "j": null,
        "u": null
      },
      {
        "n": "DJ Moement",
        "s": "2026-04-14T04:00:00Z",
        "e": "2026-04-14T05:00:00Z",
        "d": null,
        "j": null,
        "u": null,
        "t": "monthly",
        "p": "djmoement"
      },
      {
        "n": "Sparring Sessions",
        "s": "2026-04-14T06:00:00Z",
        "e": "2026-04-14T07:00:00Z",
        "d": null,
        "j": null,
        "u": null,
        "t": "monthly"
      },
      {
        "n": "Breakfast Spoons w/ Boruch",
        "s": "2026-04-14T07:00:00Z",
        "e": "2026-04-14T08:00:00Z",
        "d": null,
        "j": "Boruch",
        "u": null,
        "t": "monthly"
      },
      {
        "n": "Gingerly",
        "s": "2026-04-14T08:00:00Z",
        "e": "2026-04-14T09:00:00Z",
        "d": null,
        "j": null,
        "u": null,
        "t": "monthly"
      },
      {
        "n": "Lucidik ",
        "s": "2026-04-14T10:00:00Z",
        "e": "2026-04-14T11:00:00Z",
        "d": null,
        "j": null,
        "u": null,
        "t": "monthly"
      },
      {
        "n": "Radio Roshy",
        "s": "2026-04-14T11:00:00Z",
        "e": "2026-04-14T12:00:00Z",
        "d": null,
        "j": null,
        "u": null,
        "t": "monthly",
        "p": "radioroshy"
      },
      {
        "n": "CONE",
        "s": "2026-04-14T12:00:00Z",
        "e": "2026-04-14T13:00:00Z",
        "d": null,
        "j": null,
        "u": null,
        "t": "monthly",
        "p": "cone"
      },
      {
        "n": "Hyrah ",
        "s": "2026-04-14T13:00:00Z",
        "e": "2026-04-14T14:00:00Z",
        "d": null,
        "j": null,
        "u": null,
        "t": "monthly",
        "p": "hyrah"
      },
      {
        "n": "Jimmy2Shoes",
        "s": "2026-04-14T15:00:00Z",
        "e": "2026-04-14T16:00:00Z",
        "d": "Rolling through varied tempo's and genres, Jimmy 2 Shoes brings dance floor orientated vibes and flows to wriggle your toes to. Expect eclectic selections and the freshest sounds from the UK underground. ",
        "j": null,
        "u": null,
        "t": "monthly"
      },
      {
        "n": "Captain Lew",
        "s": "2026-04-14T16:00:00Z",
        "e": "2026-04-14T17:00:00Z",
        "d": null,
        "j": null,
        "u": null,
        "t": "monthly"
      },
      {
        "n": "Bardusco",
        "s": "2026-04-14T17:00:00Z",
        "e": "2026-04-14T18:00:00Z",
        "d": null,
        "j": null,
        "u": null,
        "t": "monthly"
      },
      {
        "n": "Gasp w/ Gabreal",
        "s": "2026-04-14T18:00:00Z",
        "e": "2026-04-14T19:00:00Z",
        "d": null,
        "j": "Gabreal",
        "u": null,
        "t": "monthly"
      },
      {
        "n": "Rodney",
        "s": "2026-04-14T19:00:00Z",
        "e": "2026-04-14T20:00:00Z",
        "d": null,
        "j": null,
        "u": null,
        "t": "monthly",
        "p": "rodney"
      },
      {
        "n": "The Wheel Up Show w/ Tripta",
        "s": "2026-04-14T21:00:00Z",
        "e": "2026-04-14T22:00:00Z",
        "d": "Tripta is a Toronto based producer/DJ focusing on the darker sounds of Grime. Also blending elements of Drill, Dubstep and even Jungle all together for a unique sound you won't hear anywhere else. Signed to Slimzee's 'Slimzo's Recordings' and ‘Rotpot Records’.",
        "j": "Tripta",
        "u": null,
        "t": "monthly"
      },
      {
        "n": "Jonny Z",
        "s": "2026-04-14T22:00:00Z",
        "e": "2026-04-14T23:00:00Z",
        "d": null,
        "j": null,
        "u": null,
        "t": "monthly"
      },
      {
        "n": "Deens",
        "s": "2026-04-14T23:00:00Z",
        "e": "2026-04-15T00:00:00Z",
        "d": null,
        "j": null,
        "u": null,
        "t": "monthly"
      },
      {
        "n": "Wrong number",
        "s": "2026-04-15T00:00:00Z",
        "e": "2026-04-15T01:00:00Z",
        "d": null,
        "j": null,
        "u": null
      },
      {
        "n": "Sub Archives",
        "s": "2026-04-15T01:00:00Z",
        "e": "2026-04-15T02:00:00Z",
        "d": null,
        "j": null,
        "u": null,
        "t": "monthly",
        "p": "subarchives"
      },
      {
        "n": "Baghead",
        "s": "2026-04-15T02:00:00Z",
        "e": "2026-04-15T03:00:00Z",
        "d": null,
        "j": null,
        "u": null,
        "t": "monthly"
      },
      {
        "n": "SJH",
        "s": "2026-04-15T06:00:00Z",
        "e": "2026-04-15T07:00:00Z",
        "d": null,
        "j": null,
        "u": null,
        "t": "monthly",
        "p": "sjh"
      },
      {
        "n": "BLACK SHEEP RADIO by LEFTY",
        "s": "2026-04-15T07:00:00Z",
        "e": "2026-04-15T08:00:00Z",
        "d": null,
        "j": null,
        "u": null,
        "t": "monthly"
      },
      {
        "n": "TSZ INVITES FITS ME FUNNY",
        "s": "2026-04-15T08:00:00Z",
        "e": "2026-04-15T10:00:00Z",
        "d": null,
        "j": null,
        "u": null,
        "t": "monthly"
      },
      {
        "n": "Stroke of Sound by Tia",
        "s": "2026-04-15T11:00:00Z",
        "e": "2026-04-15T12:00:00Z",
        "d": null,
        "j": null,
        "u": null,
        "t": "monthly",
        "p": "tia"
      },
      {
        "n": "0x54",
        "s": "2026-04-15T12:00:00Z",
        "e": "2026-04-15T13:00:00Z",
        "d": null,
        "j": null,
        "u": null,
        "t": "monthly",
        "p": "0x54"
      },
      {
        "n": "Nabes",
        "s": "2026-04-15T13:00:00Z",
        "e": "2026-04-15T14:00:00Z",
        "d": null,
        "j": null,
        "u": null,
        "t": "monthly",
        "p": "nabes"
      },
      {
        "n": "Lo5ive",
        "s": "2026-04-15T14:00:00Z",
        "e": "2026-04-15T15:00:00Z",
        "d": null,
        "j": null,
        "u": null,
        "t": "monthly"
      },
      {
        "n": " Gilbo",
        "s": "2026-04-15T15:00:00Z",
        "e": "2026-04-15T16:00:00Z",
        "d": null,
        "j": null,
        "u": null,
        "t": "monthly",
        "p": "gilbo"
      },
      {
        "n": "MixRaw",
        "s": "2026-04-15T16:00:00Z",
        "e": "2026-04-15T17:00:00Z",
        "d": null,
        "j": null,
        "u": null,
        "t": "monthly"
      },
      {
        "n": " Antisocial Records",
        "s": "2026-04-15T17:00:00Z",
        "e": "2026-04-15T18:00:00Z",
        "d": null,
        "j": null,
        "u": null,
        "t": "monthly",
        "p": "antisocialrecords"
      },
      {
        "n": "Rebekah Abdeen",
        "s": "2026-04-15T18:00:00Z",
        "e": "2026-04-15T19:00:00Z",
        "d": null,
        "j": null,
        "u": null,
        "t": "monthly"
      },
      {
        "n": "Sumgii",
        "s": "2026-04-15T19:00:00Z",
        "e": "2026-04-15T21:00:00Z",
        "d": null,
        "j": null,
        "u": null,
        "t": "monthly"
      }
    ],
    "dublab": [
      {
        "n": "Jeff Weiss - POW Radio",
        "s": "2026-04-08T19:00:00Z",
        "e": "2026-04-08T21:00:00Z",
        "d": null,
        "j": "POW Radio",
        "u": null,
        "t": "monthly",
        "p": "jeffweiss"
      },
      {
        "n": "Danny Holloway - Heads Up",
        "s": "2026-04-08T21:00:00Z",
        "e": "2026-04-08T23:00:00Z",
        "d": null,
        "j": "Heads Up",
        "u": null,
        "t": "monthly",
        "p": "dannyholloway",
        "ap": [
          "holloway"
        ]
      },
      {
        "n": "Byron Westbrook - Chromatic Fields",
        "s": "2026-04-08T23:00:00Z",
        "e": "2026-04-09T01:00:00Z",
        "d": null,
        "j": "Chromatic Fields",
        "u": null,
        "t": "monthly",
        "p": "byronwestbrook"
      },
      {
        "n": "Rusty Santos - Microworlds",
        "s": "2026-04-09T03:00:00Z",
        "e": "2026-04-09T05:00:00Z",
        "d": null,
        "j": "Microworlds",
        "u": null,
        "t": "monthly",
        "p": "rustysantos"
      },
      {
        "n": "Laura Shumate - Indoor Cats",
        "s": "2026-04-09T05:00:00Z",
        "e": "2026-04-09T07:00:00Z",
        "d": null,
        "j": "Indoor Cats",
        "u": null,
        "t": "monthly",
        "p": "laurashumate"
      },
      {
        "n": "LARAAJI and OUT THERE",
        "s": "2026-04-09T15:30:00Z",
        "e": "2026-04-09T16:00:00Z",
        "d": null,
        "j": null,
        "u": null,
        "t": "weekly"
      },
      {
        "n": "Heavy Trip – Inner Ear",
        "s": "2026-04-09T16:00:00Z",
        "e": "2026-04-09T17:00:00Z",
        "d": null,
        "j": null,
        "u": null,
        "t": "monthly",
        "p": "heavytrip"
      },
      {
        "n": "EDICA+ - Dub & Effection",
        "s": "2026-04-09T17:00:00Z",
        "e": "2026-04-09T19:00:00Z",
        "d": null,
        "j": "Dub & Effection",
        "u": null,
        "t": "monthly",
        "p": "edica"
      },
      {
        "n": "Jimmy Tamborello - Dying Songs",
        "s": "2026-04-09T19:00:00Z",
        "e": "2026-04-09T21:00:00Z",
        "d": "“Dying Songs focuses on melancholic electronic music but isn’t limited to that. Sometimes it gets dark, sometimes I try to mix techno awkwardly, sometimes i get nostalgic… I like stuff that’s dreamy, ghostly, pretty and sad. I’ll try out new productions of my own, as well. I’m keeping it pretty open and we’ll see how it evolves.” – Jimmy",
        "j": "Dying Songs",
        "u": null,
        "t": "weekly",
        "p": "jimmytamborello"
      },
      {
        "n": "Hannah Rubin and Noelle Armstrong – MELLOW DRAMA",
        "s": "2026-04-09T21:00:00Z",
        "e": "2026-04-09T23:00:00Z",
        "d": null,
        "j": null,
        "u": null,
        "t": "monthly",
        "p": "hannah",
        "ap": [
          "hannahrubin",
          "noellearmstrong"
        ]
      },
      {
        "n": "Frankie Jax No Mad - Not Evil Radio",
        "s": "2026-04-09T23:00:00Z",
        "e": "2026-04-10T01:00:00Z",
        "d": null,
        "j": "Not Evil Radio",
        "u": null,
        "t": "monthly",
        "p": "frankiejaxnomad"
      },
      {
        "n": "Frosty - Celsius Drop",
        "s": "2026-04-10T01:00:00Z",
        "e": "2026-04-10T03:00:00Z",
        "d": null,
        "j": "Celsius Drop",
        "u": null,
        "t": "monthly",
        "p": "frosty"
      },
      {
        "n": "Grotto",
        "s": "2026-04-10T03:00:00Z",
        "e": "2026-04-10T05:00:00Z",
        "d": null,
        "j": null,
        "u": null
      },
      {
        "n": "Alex Pelly - PELLYVISION",
        "s": "2026-04-10T05:00:00Z",
        "e": "2026-04-10T07:00:00Z",
        "d": null,
        "j": "PELLYVISION",
        "u": null,
        "t": "monthly",
        "p": "alexpelly"
      },
      {
        "n": "EddyMac - Something Going On",
        "s": "2026-04-10T15:00:00Z",
        "e": "2026-04-10T17:00:00Z",
        "d": null,
        "j": "Something Going On",
        "u": null,
        "t": "monthly",
        "p": "eddymac"
      },
      {
        "n": "Daddy Differently and Dirty Dave - Things of Life",
        "s": "2026-04-10T17:00:00Z",
        "e": "2026-04-10T19:00:00Z",
        "d": "It’s the simple things isn’t it? The little things of life. Good food, sunshine, no traffic, dark coffee, 72˚ breeze, telephone off the hook and music every Friday morning a la Daddy Differently & Dirty Dave.",
        "j": "Things of Life",
        "u": null,
        "t": "weekly",
        "p": "daddydifferently",
        "ap": [
          "dirtydave"
        ]
      },
      {
        "n": "Xica Soul - SoundProof",
        "s": "2026-04-10T19:00:00Z",
        "e": "2026-04-10T21:00:00Z",
        "d": null,
        "j": "SoundProof",
        "u": null,
        "t": "monthly",
        "p": "xicasoul"
      },
      {
        "n": "DJ Bird of Paradigm –  Paradigm Power Hour",
        "s": "2026-04-10T21:00:00Z",
        "e": "2026-04-10T22:00:00Z",
        "d": null,
        "j": null,
        "u": null,
        "t": "monthly",
        "p": "birdofparadigm"
      },
      {
        "n": "DJ The Witching Hours - Centrifugues",
        "s": "2026-04-10T22:00:00Z",
        "e": "2026-04-10T23:00:00Z",
        "d": null,
        "j": "Centrifugues",
        "u": null,
        "t": "monthly",
        "p": "djthewitchinghours"
      },
      {
        "n": "Matt McDermott – En Plein Air",
        "s": "2026-04-10T23:00:00Z",
        "e": "2026-04-11T01:00:00Z",
        "d": null,
        "j": null,
        "u": null,
        "t": "monthly",
        "p": "mattmcdermott"
      },
      {
        "n": "Gum.mp3 - Black Audio Society",
        "s": "2026-04-11T01:00:00Z",
        "e": "2026-04-11T03:00:00Z",
        "d": null,
        "j": "Black Audio Society",
        "u": null,
        "t": "monthly"
      },
      {
        "n": "88 - Club Paradise",
        "s": "2026-04-11T05:00:00Z",
        "e": "2026-04-11T07:00:00Z",
        "d": null,
        "j": "Club Paradise",
        "u": null,
        "t": "monthly",
        "p": "88",
        "ap": [
          "paradise"
        ]
      },
      {
        "n": "sounds of NOW",
        "s": "2026-04-11T07:00:00Z",
        "e": "2026-04-11T09:00:00Z",
        "d": null,
        "j": null,
        "u": null,
        "t": "playlist"
      },
      {
        "n": "sounds of NOW",
        "s": "2026-04-11T11:00:00Z",
        "e": "2026-04-11T15:00:00Z",
        "d": null,
        "j": null,
        "u": null,
        "t": "playlist"
      },
      {
        "n": "Ill Camille x Jesse Fairfax - The Sweeter the Juice",
        "s": "2026-04-11T15:00:00Z",
        "e": "2026-04-11T17:00:00Z",
        "d": null,
        "j": "The Sweeter the Juice",
        "u": null,
        "t": "biweekly",
        "p": "illcamille"
      },
      {
        "n": "Ryan Lee Moore – Holy Ghost Honky Tonk",
        "s": "2026-04-11T17:00:00Z",
        "e": "2026-04-11T19:00:00Z",
        "d": null,
        "j": null,
        "u": null,
        "t": "monthly",
        "p": "ryanleemoore"
      },
      {
        "n": "Nia Michelle, Jordan Collins, Lewis Thompson – Channels",
        "s": "2026-04-11T20:00:00Z",
        "e": "2026-04-11T21:00:00Z",
        "d": null,
        "j": null,
        "u": null,
        "t": "monthly",
        "p": "jordancollins",
        "ap": [
          "lewisthompson",
          "niamichelle"
        ]
      },
      {
        "n": "D Tiberio - Patterns of Lorena",
        "s": "2026-04-11T21:00:00Z",
        "e": "2026-04-11T23:00:00Z",
        "d": null,
        "j": "Patterns of Lorena",
        "u": null,
        "t": "monthly",
        "p": "dtiberio"
      },
      {
        "n": "Ravedad - Serenity Rave",
        "s": "2026-04-11T23:00:00Z",
        "e": "2026-04-12T01:00:00Z",
        "d": null,
        "j": "Serenity Rave",
        "u": null,
        "t": "monthly",
        "p": "ravedad"
      },
      {
        "n": "sodapop - sodapop sounds",
        "s": "2026-04-12T01:00:00Z",
        "e": "2026-04-12T03:00:00Z",
        "d": null,
        "j": "sodapop sounds",
        "u": null,
        "t": "monthly",
        "p": "sodapop"
      },
      {
        "n": "Daedelus - Entropy Sessions",
        "s": "2026-04-12T05:00:00Z",
        "e": "2026-04-12T07:00:00Z",
        "d": null,
        "j": "Entropy Sessions",
        "u": null,
        "t": "monthly",
        "p": "daedelus"
      },
      {
        "n": "djjs",
        "s": "2026-04-12T12:00:00Z",
        "e": "2026-04-12T14:00:00Z",
        "d": null,
        "j": null,
        "u": null,
        "t": "playlist"
      },
      {
        "n": "djjs 2",
        "s": "2026-04-12T14:00:00Z",
        "e": "2026-04-12T16:00:00Z",
        "d": null,
        "j": null,
        "u": null,
        "t": "playlist"
      },
      {
        "n": "Kenneth Bager - Music for Dreams",
        "s": "2026-04-12T16:00:00Z",
        "e": "2026-04-12T17:00:00Z",
        "d": null,
        "j": "Music for Dreams",
        "u": null,
        "t": "weekly",
        "p": "kennethbager"
      },
      {
        "n": "Bob Baker Marionette Theater – Puppetphonic",
        "s": "2026-04-12T17:00:00Z",
        "e": "2026-04-12T19:00:00Z",
        "d": null,
        "j": null,
        "u": null,
        "t": "monthly"
      },
      {
        "n": "Becky Ebenkamp – Bubblegum & Other Delights",
        "s": "2026-04-12T19:00:00Z",
        "e": "2026-04-12T21:00:00Z",
        "d": null,
        "j": null,
        "u": null,
        "t": "monthly",
        "p": "beckyebenkamp"
      },
      {
        "n": "gfunktrece - Escuchar al Istmo",
        "s": "2026-04-12T21:00:00Z",
        "e": "2026-04-12T23:00:00Z",
        "d": null,
        "j": "Escuchar al Istmo",
        "u": null,
        "t": "monthly",
        "p": "gfunktrece"
      },
      {
        "n": "DJ Lady C - Rare Air",
        "s": "2026-04-12T23:00:00Z",
        "e": "2026-04-13T01:00:00Z",
        "d": null,
        "j": "Rare Air",
        "u": null,
        "t": "monthly",
        "p": "djladyc"
      },
      {
        "n": "McAllister and Kyle Art Threat - Please and Thank You",
        "s": "2026-04-13T01:00:00Z",
        "e": "2026-04-13T03:00:00Z",
        "d": null,
        "j": "Please and Thank You",
        "u": null,
        "t": "monthly"
      },
      {
        "n": "DMM - Loosely Attached",
        "s": "2026-04-13T03:00:00Z",
        "e": "2026-04-13T05:00:00Z",
        "d": null,
        "j": "Loosely Attached",
        "u": null,
        "t": "monthly",
        "p": "dmm"
      },
      {
        "n": "sounds of NOW",
        "s": "2026-04-13T05:00:00Z",
        "e": "2026-04-13T07:00:00Z",
        "d": null,
        "j": null,
        "u": null,
        "t": "playlist"
      },
      {
        "n": "Middle Pillar Sounds",
        "s": "2026-04-13T15:00:00Z",
        "e": "2026-04-13T17:00:00Z",
        "d": null,
        "j": null,
        "u": null,
        "t": "monthly"
      },
      {
        "n": "Rene Contreras - Viva! Talks",
        "s": "2026-04-13T17:00:00Z",
        "e": "2026-04-13T19:00:00Z",
        "d": null,
        "j": "Viva! Talks",
        "u": null,
        "t": "weekly",
        "p": "renecontreras"
      },
      {
        "n": "Colloboh - Everything Inbetween",
        "s": "2026-04-13T19:00:00Z",
        "e": "2026-04-13T21:00:00Z",
        "d": null,
        "j": "Everything Inbetween",
        "u": null,
        "t": "monthly",
        "p": "colloboh"
      },
      {
        "n": "Terrell Brooke – TheyHouse",
        "s": "2026-04-14T01:00:00Z",
        "e": "2026-04-14T03:00:00Z",
        "d": null,
        "j": null,
        "u": null,
        "t": "monthly",
        "p": "terrellbrooke"
      },
      {
        "n": "Aaron Paar - Stomping Grounds",
        "s": "2026-04-14T03:00:00Z",
        "e": "2026-04-14T05:00:00Z",
        "d": null,
        "j": "Stomping Grounds",
        "u": null,
        "t": "biweekly",
        "p": "aaronpaar"
      },
      {
        "n": "Daniel T - Crosseyed and Painless",
        "s": "2026-04-14T05:00:00Z",
        "e": "2026-04-14T07:00:00Z",
        "d": null,
        "j": "Crosseyed and Painless",
        "u": null,
        "t": "monthly",
        "p": "danielt"
      },
      {
        "n": "Mike Harding and Bana Haffar - Long Wave",
        "s": "2026-04-14T15:00:00Z",
        "e": "2026-04-14T17:00:00Z",
        "d": null,
        "j": "Long Wave",
        "u": null,
        "t": "monthly",
        "p": "banahaffar",
        "ap": [
          "mikeharding"
        ]
      },
      {
        "n": "Jeremiah Chiu – Some All None",
        "s": "2026-04-14T17:00:00Z",
        "e": "2026-04-14T19:00:00Z",
        "d": null,
        "j": null,
        "u": null,
        "t": "monthly",
        "p": "jeremiahchiu"
      },
      {
        "n": "Sonrisita – Butterfly Beat",
        "s": "2026-04-14T19:00:00Z",
        "e": "2026-04-14T21:00:00Z",
        "d": null,
        "j": null,
        "u": null,
        "t": "monthly",
        "p": "sonrisita"
      },
      {
        "n": "Hoseh - Version Sounds",
        "s": "2026-04-14T23:00:00Z",
        "e": "2026-04-15T01:00:00Z",
        "d": null,
        "j": "Version Sounds",
        "u": null,
        "t": "weekly",
        "p": "hoseh"
      },
      {
        "n": "Universe Brain - Dream Fantasy Nightmare",
        "s": "2026-04-15T01:00:00Z",
        "e": "2026-04-15T03:00:00Z",
        "d": null,
        "j": "Dream Fantasy Nightmare",
        "u": null,
        "t": "monthly",
        "p": "universebrain"
      },
      {
        "n": "Echo Park Film Center - Optical Track",
        "s": "2026-04-15T03:00:00Z",
        "e": "2026-04-15T05:00:00Z",
        "d": null,
        "j": "Optical Track",
        "u": null,
        "t": "weekly",
        "p": "echoparkfilmcenter"
      },
      {
        "n": "J.TRIPP - DWELL TIME",
        "s": "2026-04-15T05:00:00Z",
        "e": "2026-04-15T07:00:00Z",
        "d": null,
        "j": "DWELL TIME",
        "u": null,
        "t": "monthly"
      },
      {
        "n": "Teen Daze - Easy Listening",
        "s": "2026-04-15T15:00:00Z",
        "e": "2026-04-15T17:00:00Z",
        "d": null,
        "j": "Easy Listening",
        "u": null,
        "t": "monthly",
        "p": "teendaze"
      },
      {
        "n": "Heidi Lawden – Magic Roundabout",
        "s": "2026-04-15T19:00:00Z",
        "e": "2026-04-15T21:00:00Z",
        "d": null,
        "j": null,
        "u": null,
        "t": "monthly",
        "p": "heidilawden"
      }
    ],
    "rinse": [
      {
        "n": "Machinedrum",
        "s": "2026-04-08T19:00:00Z",
        "e": "2026-04-08T21:00:00Z",
        "d": null,
        "j": "DBridge, Om Unit & Fracture: From The Vault (2015)",
        "u": null,
        "p": "fracture",
        "ap": [
          "machinedrum",
          "omunit"
        ]
      },
      {
        "n": "Studio Barnhus",
        "s": "2026-04-08T21:00:00Z",
        "e": "2026-04-08T22:00:00Z",
        "d": null,
        "j": "FaltyDL",
        "u": null,
        "t": "biweekly",
        "p": "studiobarnhus"
      },
      {
        "n": "Fracture",
        "s": "2026-04-08T22:00:00Z",
        "e": "2026-04-08T23:00:00Z",
        "d": null,
        "j": null,
        "u": null,
        "t": "weekly",
        "p": "fracture"
      },
      {
        "n": "EMA",
        "s": "2026-04-08T23:00:00Z",
        "e": "2026-04-09T00:00:00Z",
        "d": null,
        "j": null,
        "u": null,
        "p": "ema"
      },
      {
        "n": "MoMA Ready",
        "s": "2026-04-09T00:00:00Z",
        "e": "2026-04-09T01:00:00Z",
        "d": null,
        "j": null,
        "u": null,
        "p": "momaready"
      },
      {
        "n": "DJ RED",
        "s": "2026-04-09T01:00:00Z",
        "e": "2026-04-09T02:00:00Z",
        "d": null,
        "j": null,
        "u": null,
        "t": "biweekly"
      },
      {
        "n": "Playlist",
        "s": "2026-04-09T02:00:00Z",
        "e": "2026-04-09T05:00:00Z",
        "d": null,
        "j": null,
        "u": null,
        "t": "playlist"
      },
      {
        "n": "LILA",
        "s": "2026-04-09T05:00:00Z",
        "e": "2026-04-09T06:00:00Z",
        "d": null,
        "j": null,
        "u": null,
        "p": "lila"
      },
      {
        "n": "Playlist",
        "s": "2026-04-09T06:00:00Z",
        "e": "2026-04-09T08:00:00Z",
        "d": null,
        "j": null,
        "u": null,
        "t": "playlist"
      },
      {
        "n": "Yazmin Lacey",
        "s": "2026-04-09T08:00:00Z",
        "e": "2026-04-09T10:00:00Z",
        "d": null,
        "j": null,
        "u": null,
        "t": "weekly",
        "p": "yazminlacey"
      },
      {
        "n": "Chunky",
        "s": "2026-04-09T10:00:00Z",
        "e": "2026-04-09T11:00:00Z",
        "d": null,
        "j": "Owen Osapien, Bakey, Hakeem Jr.",
        "u": null,
        "t": "biweekly",
        "p": "bakey",
        "ap": [
          "chunky"
        ]
      },
      {
        "n": "Elle Clark",
        "s": "2026-04-09T11:00:00Z",
        "e": "2026-04-09T12:00:00Z",
        "d": null,
        "j": null,
        "u": null,
        "t": "biweekly",
        "p": "elleclark"
      },
      {
        "n": "SK Vibemaker",
        "s": "2026-04-09T12:00:00Z",
        "e": "2026-04-09T13:00:00Z",
        "d": null,
        "j": "Elmiene",
        "u": null,
        "t": "weekly",
        "p": "skvibemaker"
      },
      {
        "n": "Omar+",
        "s": "2026-04-09T13:00:00Z",
        "e": "2026-04-09T14:00:00Z",
        "d": null,
        "j": null,
        "u": null,
        "t": "monthly"
      },
      {
        "n": "Tom Ravenscroft",
        "s": "2026-04-09T14:00:00Z",
        "e": "2026-04-09T16:00:00Z",
        "d": null,
        "j": null,
        "u": null,
        "t": "weekly",
        "p": "tomravenscroft"
      },
      {
        "n": "Adventures In Paradise with Manuel Darquart",
        "s": "2026-04-09T16:00:00Z",
        "e": "2026-04-09T17:00:00Z",
        "d": null,
        "j": "Good Block",
        "u": null,
        "t": "monthly",
        "p": "manueldarquart",
        "ap": [
          "paradise"
        ]
      },
      {
        "n": "Maey",
        "s": "2026-04-09T17:00:00Z",
        "e": "2026-04-09T18:00:00Z",
        "d": null,
        "j": null,
        "u": null,
        "t": "weekly",
        "p": "maey"
      },
      {
        "n": "RUTHLSS",
        "s": "2026-04-09T18:00:00Z",
        "e": "2026-04-09T19:00:00Z",
        "d": null,
        "j": null,
        "u": null,
        "t": "monthly",
        "p": "ruthlss"
      },
      {
        "n": "KILIMANJARO",
        "s": "2026-04-09T19:00:00Z",
        "e": "2026-04-09T21:00:00Z",
        "d": null,
        "j": "El Makuka",
        "u": null,
        "t": "monthly",
        "p": "kilimanjaro"
      },
      {
        "n": "Jacques Greene",
        "s": "2026-04-09T21:00:00Z",
        "e": "2026-04-09T22:00:00Z",
        "d": null,
        "j": null,
        "u": null,
        "t": "biweekly",
        "p": "jacquesgreene"
      },
      {
        "n": "YETI OUT",
        "s": "2026-04-09T22:00:00Z",
        "e": "2026-04-09T23:00:00Z",
        "d": null,
        "j": null,
        "u": null
      }
    ],
    "rinsefr": [
      {
        "n": "Playlist France",
        "s": "2026-04-08T19:00:00Z",
        "e": "2026-04-08T22:00:00Z",
        "d": null,
        "j": null,
        "u": null,
        "t": "playlist"
      },
      {
        "n": "Playlist France",
        "s": "2026-04-08T22:00:00Z",
        "e": "2026-04-09T07:00:00Z",
        "d": null,
        "j": null,
        "u": null,
        "t": "playlist"
      },
      {
        "n": "Playlist France",
        "s": "2026-04-09T07:00:00Z",
        "e": "2026-04-09T12:00:00Z",
        "d": null,
        "j": null,
        "u": null,
        "t": "playlist"
      },
      {
        "n": "JP MANO",
        "s": "2026-04-09T12:00:00Z",
        "e": "2026-04-09T14:00:00Z",
        "d": null,
        "j": "On Parle Musique",
        "u": null,
        "t": "monthly"
      },
      {
        "n": "Tysha Cee",
        "s": "2026-04-09T14:00:00Z",
        "e": "2026-04-09T15:00:00Z",
        "d": null,
        "j": null,
        "u": null,
        "t": "monthly",
        "p": "tyshacee"
      },
      {
        "n": "Maquis Sale",
        "s": "2026-04-09T15:00:00Z",
        "e": "2026-04-09T16:00:00Z",
        "d": null,
        "j": null,
        "u": null
      },
      {
        "n": "Bad Tips",
        "s": "2026-04-09T16:00:00Z",
        "e": "2026-04-09T17:00:00Z",
        "d": null,
        "j": "Yenkov",
        "u": null,
        "t": "monthly"
      },
      {
        "n": "Vitaline b2b Camporeale",
        "s": "2026-04-09T17:00:00Z",
        "e": "2026-04-09T18:00:00Z",
        "d": null,
        "j": null,
        "u": null
      },
      {
        "n": "XX LAB avec François X",
        "s": "2026-04-09T18:00:00Z",
        "e": "2026-04-09T19:00:00Z",
        "d": null,
        "j": null,
        "u": null,
        "p": "xxlabavecfranoisx"
      },
      {
        "n": "Playlist France",
        "s": "2026-04-09T19:00:00Z",
        "e": "2026-04-09T20:00:00Z",
        "d": null,
        "j": null,
        "u": null,
        "t": "playlist"
      }
    ],
    "newtown": [
      {
        "n": "THIRD ROOM RADIO",
        "s": "2026-04-08T20:00:00Z",
        "e": "2026-04-08T22:00:00Z",
        "d": null,
        "j": null,
        "u": null,
        "t": "biweekly"
      },
      {
        "n": "KNOWLEDGE W/ Young link",
        "s": "2026-04-08T22:00:00Z",
        "e": "2026-04-09T00:00:00Z",
        "d": null,
        "j": "Young link",
        "u": null,
        "t": "biweekly"
      },
      {
        "n": "CHUNKS",
        "s": "2026-04-09T00:00:00Z",
        "e": "2026-04-09T02:00:00Z",
        "d": null,
        "j": null,
        "u": null,
        "t": "biweekly"
      },
      {
        "n": "ORGANIZED DISORDER",
        "s": "2026-04-09T02:00:00Z",
        "e": "2026-04-09T04:00:00Z",
        "d": null,
        "j": null,
        "u": null,
        "t": "monthly"
      },
      {
        "n": "OPEN",
        "s": "2026-04-09T04:00:00Z",
        "e": "2026-04-09T06:00:00Z",
        "d": null,
        "j": null,
        "u": null,
        "t": "playlist"
      },
      {
        "n": "Restream",
        "s": "2026-04-09T06:00:00Z",
        "e": "2026-04-09T12:00:00Z",
        "d": null,
        "j": null,
        "u": null,
        "t": "restream"
      },
      {
        "n": "STRETCHES",
        "s": "2026-04-09T12:00:00Z",
        "e": "2026-04-09T13:00:00Z",
        "d": null,
        "j": null,
        "u": null,
        "t": "biweekly"
      },
      {
        "n": "EXTRA SPICY PLEASE",
        "s": "2026-04-09T13:00:00Z",
        "e": "2026-04-09T15:00:00Z",
        "d": null,
        "j": null,
        "u": null,
        "t": "biweekly"
      },
      {
        "n": "1000 LTR SHOW",
        "s": "2026-04-09T15:00:00Z",
        "e": "2026-04-09T17:00:00Z",
        "d": null,
        "j": null,
        "u": null,
        "t": "biweekly"
      },
      {
        "n": "LET'S TALK HIP HOP",
        "s": "2026-04-09T17:00:00Z",
        "e": "2026-04-09T19:00:00Z",
        "d": null,
        "j": null,
        "u": null,
        "t": "biweekly"
      },
      {
        "n": "HONEY CAFE",
        "s": "2026-04-09T19:00:00Z",
        "e": "2026-04-09T21:00:00Z",
        "d": null,
        "j": null,
        "u": null,
        "t": "biweekly",
        "p": "honey"
      },
      {
        "n": "NICE PULP RADIO",
        "s": "2026-04-09T21:00:00Z",
        "e": "2026-04-09T23:00:00Z",
        "d": null,
        "j": null,
        "u": null,
        "t": "biweekly"
      },
      {
        "n": "SPECTACLE RADIO",
        "s": "2026-04-09T23:00:00Z",
        "e": "2026-04-10T01:00:00Z",
        "d": null,
        "j": null,
        "u": null,
        "t": "biweekly"
      },
      {
        "n": "2012 AFTERLIFE",
        "s": "2026-04-10T01:00:00Z",
        "e": "2026-04-10T03:00:00Z",
        "d": null,
        "j": null,
        "u": null,
        "t": "weekly"
      },
      {
        "n": "HEADCRACK",
        "s": "2026-04-10T03:00:00Z",
        "e": "2026-04-10T05:00:00Z",
        "d": null,
        "j": null,
        "u": null,
        "t": "biweekly"
      },
      {
        "n": "Restream",
        "s": "2026-04-10T05:00:00Z",
        "e": "2026-04-10T12:00:00Z",
        "d": null,
        "j": null,
        "u": null,
        "t": "restream"
      },
      {
        "n": "GRAVITATION",
        "s": "2026-04-10T12:00:00Z",
        "e": "2026-04-10T13:00:00Z",
        "d": null,
        "j": null,
        "u": null,
        "t": "weekly"
      },
      {
        "n": "HANGTIME RADIO",
        "s": "2026-04-10T13:00:00Z",
        "e": "2026-04-10T15:00:00Z",
        "d": null,
        "j": null,
        "u": null,
        "t": "weekly"
      },
      {
        "n": "VIBES WITH GIN",
        "s": "2026-04-10T15:00:00Z",
        "e": "2026-04-10T17:00:00Z",
        "d": null,
        "j": null,
        "u": null,
        "t": "biweekly"
      },
      {
        "n": "TARZAN CITY",
        "s": "2026-04-10T17:00:00Z",
        "e": "2026-04-10T19:00:00Z",
        "d": null,
        "j": null,
        "u": null,
        "t": "monthly"
      },
      {
        "n": "SLIGHT OF HAND",
        "s": "2026-04-10T19:00:00Z",
        "e": "2026-04-10T21:00:00Z",
        "d": null,
        "j": null,
        "u": null,
        "t": "biweekly"
      },
      {
        "n": "EETHR PRESENTS",
        "s": "2026-04-10T21:00:00Z",
        "e": "2026-04-10T23:00:00Z",
        "d": null,
        "j": null,
        "u": null,
        "t": "monthly"
      },
      {
        "n": "EXPLORATIONS",
        "s": "2026-04-10T23:00:00Z",
        "e": "2026-04-11T01:00:00Z",
        "d": null,
        "j": null,
        "u": null
      },
      {
        "n": "RADIO PARTY",
        "s": "2026-04-11T01:00:00Z",
        "e": "2026-04-11T04:00:00Z",
        "d": null,
        "j": null,
        "u": null,
        "t": "weekly"
      },
      {
        "n": "Restream",
        "s": "2026-04-11T04:00:00Z",
        "e": "2026-04-11T12:00:00Z",
        "d": null,
        "j": null,
        "u": null,
        "t": "restream"
      },
      {
        "n": "DON BOY 718 SPORTS",
        "s": "2026-04-11T12:00:00Z",
        "e": "2026-04-11T14:00:00Z",
        "d": null,
        "j": null,
        "u": null,
        "t": "weekly"
      },
      {
        "n": "SATURDAYS WITH MR. L",
        "s": "2026-04-11T14:00:00Z",
        "e": "2026-04-11T16:00:00Z",
        "d": null,
        "j": null,
        "u": null,
        "t": "weekly"
      },
      {
        "n": "STRANGERS LIVE",
        "s": "2026-04-11T16:00:00Z",
        "e": "2026-04-11T18:00:00Z",
        "d": null,
        "j": null,
        "u": null,
        "t": "biweekly"
      },
      {
        "n": "BOSSASAURUS TIME",
        "s": "2026-04-11T18:00:00Z",
        "e": "2026-04-11T20:00:00Z",
        "d": null,
        "j": null,
        "u": null,
        "t": "weekly"
      },
      {
        "n": "SQUINTZ & RACOONS MORNING ZOO IN THE AFTERNOON",
        "s": "2026-04-11T20:00:00Z",
        "e": "2026-04-11T22:00:00Z",
        "d": null,
        "j": null,
        "u": null,
        "t": "weekly"
      },
      {
        "n": "TURN UP THE STROBE",
        "s": "2026-04-11T22:00:00Z",
        "e": "2026-04-12T01:00:00Z",
        "d": null,
        "j": null,
        "u": null,
        "t": "monthly"
      },
      {
        "n": "THE DEN",
        "s": "2026-04-12T01:00:00Z",
        "e": "2026-04-12T03:00:00Z",
        "d": null,
        "j": null,
        "u": null,
        "t": "biweekly"
      },
      {
        "n": "STRANGE BREW RADIO",
        "s": "2026-04-12T03:00:00Z",
        "e": "2026-04-12T05:00:00Z",
        "d": null,
        "j": null,
        "u": null,
        "t": "weekly"
      },
      {
        "n": "Restream",
        "s": "2026-04-12T05:00:00Z",
        "e": "2026-04-12T12:00:00Z",
        "d": null,
        "j": null,
        "u": null,
        "t": "restream"
      },
      {
        "n": "TEN TOES DOWN",
        "s": "2026-04-12T12:00:00Z",
        "e": "2026-04-12T14:00:00Z",
        "d": null,
        "j": null,
        "u": null,
        "t": "biweekly"
      },
      {
        "n": "ROAD RHYTHM",
        "s": "2026-04-12T14:00:00Z",
        "e": "2026-04-12T15:00:00Z",
        "d": null,
        "j": null,
        "u": null,
        "t": "biweekly"
      },
      {
        "n": "HACKNEY UPON CALUMET",
        "s": "2026-04-12T15:00:00Z",
        "e": "2026-04-12T16:00:00Z",
        "d": null,
        "j": null,
        "u": null,
        "t": "monthly"
      },
      {
        "n": "MXD SGNLS",
        "s": "2026-04-12T16:00:00Z",
        "e": "2026-04-12T18:00:00Z",
        "d": null,
        "j": null,
        "u": null,
        "t": "biweekly"
      },
      {
        "n": "MILLENNIUM STONE CIRCLE",
        "s": "2026-04-12T18:00:00Z",
        "e": "2026-04-12T20:00:00Z",
        "d": null,
        "j": null,
        "u": null,
        "t": "biweekly",
        "p": "circle"
      },
      {
        "n": "GIMME TINNITUS RADIO TIME",
        "s": "2026-04-12T20:00:00Z",
        "e": "2026-04-12T22:00:00Z",
        "d": null,
        "j": null,
        "u": null,
        "t": "biweekly"
      },
      {
        "n": "COUPLES THERAPY",
        "s": "2026-04-12T22:00:00Z",
        "e": "2026-04-13T00:00:00Z",
        "d": null,
        "j": null,
        "u": null,
        "t": "biweekly"
      },
      {
        "n": "WRUG \"THE RUG\"",
        "s": "2026-04-13T00:00:00Z",
        "e": "2026-04-13T01:30:00Z",
        "d": null,
        "j": null,
        "u": null,
        "t": "biweekly"
      },
      {
        "n": "IDK.WAV RADIO",
        "s": "2026-04-13T01:30:00Z",
        "e": "2026-04-13T03:00:00Z",
        "d": null,
        "j": null,
        "u": null,
        "t": "biweekly"
      },
      {
        "n": "TRIPLEDECK",
        "s": "2026-04-13T03:00:00Z",
        "e": "2026-04-13T05:00:00Z",
        "d": null,
        "j": null,
        "u": null,
        "t": "biweekly"
      },
      {
        "n": "Restream",
        "s": "2026-04-13T05:00:00Z",
        "e": "2026-04-13T13:00:00Z",
        "d": null,
        "j": null,
        "u": null,
        "t": "restream"
      },
      {
        "n": "WHOLE MILK",
        "s": "2026-04-13T13:00:00Z",
        "e": "2026-04-13T15:00:00Z",
        "d": null,
        "j": null,
        "u": null,
        "t": "monthly"
      },
      {
        "n": "MALPRACTICE",
        "s": "2026-04-13T15:00:00Z",
        "e": "2026-04-13T17:00:00Z",
        "d": null,
        "j": null,
        "u": null,
        "t": "weekly"
      },
      {
        "n": "LO RADIO",
        "s": "2026-04-13T17:00:00Z",
        "e": "2026-04-13T19:00:00Z",
        "d": null,
        "j": null,
        "u": null,
        "t": "biweekly"
      },
      {
        "n": "SCRATCH ACADEMY",
        "s": "2026-04-13T19:00:00Z",
        "e": "2026-04-13T21:00:00Z",
        "d": null,
        "j": null,
        "u": null,
        "t": "weekly"
      },
      {
        "n": "CUMBIA SABROSURA",
        "s": "2026-04-13T21:00:00Z",
        "e": "2026-04-13T23:00:00Z",
        "d": null,
        "j": null,
        "u": null,
        "t": "biweekly"
      },
      {
        "n": "RECESS",
        "s": "2026-04-13T23:00:00Z",
        "e": "2026-04-14T01:00:00Z",
        "d": null,
        "j": null,
        "u": null,
        "t": "biweekly"
      },
      {
        "n": "TENSION/RELEASE",
        "s": "2026-04-14T01:00:00Z",
        "e": "2026-04-14T03:00:00Z",
        "d": null,
        "j": null,
        "u": null,
        "t": "biweekly"
      },
      {
        "n": "PRETTY BOY FACIAL",
        "s": "2026-04-14T03:00:00Z",
        "e": "2026-04-14T05:00:00Z",
        "d": null,
        "j": null,
        "u": null,
        "t": "biweekly"
      },
      {
        "n": "Restream",
        "s": "2026-04-14T05:00:00Z",
        "e": "2026-04-14T12:00:00Z",
        "d": null,
        "j": null,
        "u": null,
        "t": "restream"
      },
      {
        "n": "BUSS UP SHUT",
        "s": "2026-04-14T12:00:00Z",
        "e": "2026-04-14T14:00:00Z",
        "d": null,
        "j": null,
        "u": null,
        "t": "weekly"
      },
      {
        "n": "STIMULANT TUESDAYS",
        "s": "2026-04-14T14:00:00Z",
        "e": "2026-04-14T16:00:00Z",
        "d": null,
        "j": null,
        "u": null,
        "t": "biweekly"
      },
      {
        "n": "CHUNKS",
        "s": "2026-04-14T16:00:00Z",
        "e": "2026-04-14T18:00:00Z",
        "d": null,
        "j": null,
        "u": null,
        "t": "biweekly"
      },
      {
        "n": "POSt rADIO",
        "s": "2026-04-14T18:00:00Z",
        "e": "2026-04-14T20:00:00Z",
        "d": null,
        "j": null,
        "u": null,
        "t": "biweekly"
      },
      {
        "n": "FLOORPLAY",
        "s": "2026-04-14T20:00:00Z",
        "e": "2026-04-14T22:00:00Z",
        "d": null,
        "j": null,
        "u": null,
        "t": "biweekly"
      },
      {
        "n": "OPEN",
        "s": "2026-04-14T22:00:00Z",
        "e": "2026-04-15T00:00:00Z",
        "d": null,
        "j": null,
        "u": null,
        "t": "playlist"
      },
      {
        "n": "THRESHOLD_",
        "s": "2026-04-15T00:00:00Z",
        "e": "2026-04-15T02:00:00Z",
        "d": null,
        "j": null,
        "u": null,
        "t": "biweekly"
      },
      {
        "n": "DOSVU",
        "s": "2026-04-15T02:00:00Z",
        "e": "2026-04-15T04:00:00Z",
        "d": null,
        "j": null,
        "u": null,
        "t": "biweekly"
      },
      {
        "n": "Restream",
        "s": "2026-04-15T04:00:00Z",
        "e": "2026-04-15T12:00:00Z",
        "d": null,
        "j": null,
        "u": null,
        "t": "restream"
      }
    ]
  }
}