{
  "v": 2,
  "updated": "2026-01-03T03:15:57.654Z",
  "stations": {
    "nts1": [
      {
        "n": "HEARTS OF AGE W/ WILLIAM TYLER & KIERAN HEBDEN (R)",
        "s": "2026-01-02T14:00:00Z",
        "e": "2026-01-02T16:00:00Z",
        "d": "A two-hour journey between kindred spirits. Hour One, curated by William Tyler, spans cosmic folk, devotional radio, avant-garde composition, and field recordings. Hour Two, led by Kieran Hebden (Four Tet), showcases his collaborations with Tyler, including their latest album, 41 Longfield Street ‘Late 80s. ",
        "j": "WILLIAM TYLER & KIERAN HEBDEN",
        "u": "https://www.nts.live/api/v2/shows/four-tet/episodes/four-tet-hearts-of-age-w-william-tyler-kieran-hebden-15th-september-2025",
        "t": "restream"
      },
      {
        "n": "HARLEY WEIR (R)",
        "s": "2026-01-02T16:00:00Z",
        "e": "2026-01-02T17:30:00Z",
        "d": "British photographer, director and artist Harley Weir selects 90 minutes of music for NTS, spanning contemporary alt pop, triphop, indie rock and more… ",
        "j": null,
        "u": "https://www.nts.live/api/v2/shows/guests/episodes/harley-weir-27th-march-2025",
        "t": "restream"
      },
      {
        "n": "Weiland (R)",
        "s": "2026-01-02T17:30:00Z",
        "e": "2026-01-02T19:00:00Z",
        "d": "Texas-based artist Weiland - Slayworld affiliate and once a plugg rap mainstay turned synth-pop experimentalist - stops by the London studio to share an hour of music from his expansive sound world.",
        "j": null,
        "u": "https://www.nts.live/api/v2/shows/guests/episodes/weiland-21st-july-2025",
        "t": "restream"
      },
      {
        "n": "RAHEL (SPOONS) (R)",
        "s": "2026-01-02T19:00:00Z",
        "e": "2026-01-02T20:00:00Z",
        "d": "Another hour of Indonesian bangers from Rahel, NTS favourite and head of supper club Spoons.",
        "j": null,
        "u": "https://www.nts.live/api/v2/shows/guests/episodes/rahel-spoons-5th-august-2025",
        "t": "restream"
      },
      {
        "n": "ROLAS W/ ABE PEDROZA: TRISTES Y ROMÁNTICAS (R)",
        "s": "2026-01-02T20:00:00Z",
        "e": "2026-01-02T21:00:00Z",
        "d": "Abe Pedroza selects an hour of teark-jerking and romantic music from the Spanish speaking world – boleros, ballads, and moody instrumentals – “pairs well with a game of dominoes con los Tíos”.",
        "j": "ABE PEDROZA",
        "u": "https://www.nts.live/api/v2/shows/guests/episodes/rolas-w-abe-pedroza-tristes-y-romanticas-2nd-march-2025",
        "t": "restream"
      },
      {
        "n": "SNO (PHILIP TABANE, MALOMBO AND THABANG TABANE SPECIAL) (R)",
        "s": "2026-01-02T21:00:00Z",
        "e": "2026-01-02T22:00:00Z",
        "d": "Presenting music from all across the African continent and beyond, Manchester based, South African DJ SNO plays music to excite and delight your senses an hour every month.\nThis month Sno deep dives on South African guitarist and Malombo band leader Philip Tabane and his son, Thabang Tabane.",
        "j": null,
        "u": "https://www.nts.live/api/v2/shows/sno/episodes/sno-13th-may-2025",
        "t": "restream"
      },
      {
        "n": "RIO DOCE (R)",
        "s": "2026-01-02T22:00:00Z",
        "e": "2026-01-03T00:00:00Z",
        "d": "Rio Doce, a deep dive into Brazilian music and its roots, with contributions from Caio Rosa and guests.",
        "j": null,
        "u": "https://www.nts.live/api/v2/shows/rio-doce/episodes/rio-doce-26th-february-2025",
        "t": "restream"
      },
      {
        "n": "IN FOCUS: CACHAO (R)",
        "s": "2026-01-03T00:00:00Z",
        "e": "2026-01-03T01:00:00Z",
        "d": "60 minutes of sounds from the heart and soul of Cuban music, Israel López Valdés, better known simply as Cachao. Famous for being one of the original innovators of the mambbo, Cachao was a master of the art of \"descarga\": long, impassioned, flowing improvisational performances. \nMade by Hugo Mendez",
        "j": "CACHAO",
        "u": "https://www.nts.live/api/v2/shows/in-focus/episodes/in-focus-cachao-15th-august-2025",
        "t": "restream"
      },
      {
        "n": "ANNABEL FRASER (R)",
        "s": "2026-01-03T01:00:00Z",
        "e": "2026-01-03T03:00:00Z",
        "d": "Annabel Fraser is a lover of music first and foremost. Not genres. Tune in for her monthly 2 hour show…",
        "j": null,
        "u": "https://www.nts.live/api/v2/shows/annabel-fraser/episodes/annabel-fraser-25th-january-2025",
        "t": "restream"
      },
      {
        "n": "WEDNESDAY (R)",
        "s": "2026-01-03T03:00:00Z",
        "e": "2026-01-03T04:00:00Z",
        "d": "Asheville, NC indie rockers Wednesday serve up an hour of selections running the gamut of guitar music, from Polvo to Lucinda Williams. ",
        "j": null,
        "u": "https://www.nts.live/api/v2/shows/guests/episodes/wednesday-9th-october-2025",
        "t": "restream"
      },
      {
        "n": "CALM ROOTS W/ ALEX RITA (R)",
        "s": "2026-01-03T04:00:00Z",
        "e": "2026-01-03T06:00:00Z",
        "d": "Hypnotic & meditative sounds from Touching Bass' Alex Rita.",
        "j": "ALEX RITA",
        "u": "https://www.nts.live/api/v2/shows/calm-roots/episodes/calm-roots-28th-april-2025",
        "t": "restream"
      },
      {
        "n": "BO NINGEN: YUKI - SWEET NIGHTMARE MIX",
        "s": "2026-01-03T06:00:00Z",
        "e": "2026-01-03T07:00:00Z",
        "d": null,
        "j": null,
        "u": null
      },
      {
        "n": "NTS GUIDE TO: BUDDHIST CHANTS (R)",
        "s": "2026-01-03T07:00:00Z",
        "e": "2026-01-03T08:00:00Z",
        "d": null,
        "j": "BUDDHIST CHANTS",
        "u": null,
        "t": "restream"
      },
      {
        "n": "KRANKY (R)",
        "s": "2026-01-03T08:00:00Z",
        "e": "2026-01-03T09:00:00Z",
        "d": null,
        "j": null,
        "u": null,
        "t": "restream"
      },
      {
        "n": "AD 93 W/ ENYA (R)",
        "s": "2026-01-03T09:00:00Z",
        "e": "2026-01-03T11:00:00Z",
        "d": null,
        "j": "ENYA",
        "u": null,
        "t": "restream"
      },
      {
        "n": "BLOOD ORANGE & ERIKA DE CASIER (R)",
        "s": "2026-01-03T11:00:00Z",
        "e": "2026-01-03T12:00:00Z",
        "d": null,
        "j": null,
        "u": null,
        "t": "restream"
      },
      {
        "n": "KRISTIN KONTROL PRESENTS: OUT OF VOGUE (R)",
        "s": "2026-01-03T12:00:00Z",
        "e": "2026-01-03T13:00:00Z",
        "d": null,
        "j": "OUT OF VOGUE",
        "u": null,
        "t": "restream"
      },
      {
        "n": "LIQUID MIRROR W/ OLIVE KIMOTO (R)",
        "s": "2026-01-03T13:00:00Z",
        "e": "2026-01-03T14:00:00Z",
        "d": null,
        "j": "OLIVE KIMOTO",
        "u": null,
        "t": "restream"
      },
      {
        "n": "CARIBOU, FLOATING POINTS, FRED AGAIN.. – DRUMLESS SPECIAL (R)",
        "s": "2026-01-03T14:00:00Z",
        "e": "2026-01-03T16:00:00Z",
        "d": null,
        "j": null,
        "u": null,
        "t": "restream"
      },
      {
        "n": "LA COSECHA INTERNACIONAL W/ LIZZY AL TOQUE (R)",
        "s": "2026-01-03T16:00:00Z",
        "e": "2026-01-03T17:00:00Z",
        "d": null,
        "j": "LIZZY AL TOQUE",
        "u": null,
        "t": "restream"
      },
      {
        "n": "TUFF SHED W/ SPIRITUAL WORLD (R)",
        "s": "2026-01-03T17:00:00Z",
        "e": "2026-01-03T19:00:00Z",
        "d": null,
        "j": "SPIRITUAL WORLD",
        "u": null,
        "t": "restream"
      },
      {
        "n": "IN FOCUS: PAUL JOHNSON (R)",
        "s": "2026-01-03T19:00:00Z",
        "e": "2026-01-03T21:00:00Z",
        "d": null,
        "j": "PAUL JOHNSON",
        "u": null,
        "t": "restream"
      },
      {
        "n": "AQUECIMENTO W/ VHOOR & D.A.N.V (R)",
        "s": "2026-01-03T21:00:00Z",
        "e": "2026-01-03T22:00:00Z",
        "d": null,
        "j": "VHOOR & D.A.N.V",
        "u": null,
        "t": "restream"
      },
      {
        "n": "BAILE IJÓ & CAPO LEE (R)",
        "s": "2026-01-03T22:00:00Z",
        "e": "2026-01-03T23:00:00Z",
        "d": null,
        "j": null,
        "u": null,
        "t": "restream"
      },
      {
        "n": "BAIL3 DA TH4YS (R)",
        "s": "2026-01-03T23:00:00Z",
        "e": "2026-01-04T00:00:00Z",
        "d": null,
        "j": null,
        "u": null,
        "t": "restream"
      },
      {
        "n": "SEMATARY (R)",
        "s": "2026-01-04T00:00:00Z",
        "e": "2026-01-04T01:00:00Z",
        "d": null,
        "j": null,
        "u": null,
        "t": "restream"
      },
      {
        "n": "WORLDPEACE DMT - EAST ROAD (R)",
        "s": "2026-01-04T01:00:00Z",
        "e": "2026-01-04T02:00:00Z",
        "d": null,
        "j": "EAST ROAD",
        "u": null,
        "t": "restream"
      }
    ],
    "nts2": [
      {
        "n": "Healing Feeling W/ DJ Halloumi",
        "s": "2026-01-02T15:00:00Z",
        "e": "2026-01-02T16:00:00Z",
        "d": "A journey through sound that soothes the spirit and slows the pace. This mix draws from my vinyl collection and weaves soul, trip hop, dub, and acid jazz together to explore what peace feels like when it finds you. Gentle grooves, deep rhythms, and melodies that heal.",
        "j": null,
        "u": "https://www.nts.live/api/v2/shows/peace-2025/episodes/peace-2025-healing-feeling-w-dj-halloumi-2nd-january-2026"
      },
      {
        "n": "aldeia portuguesa w/ henrique?",
        "s": "2026-01-02T16:00:00Z",
        "e": "2026-01-02T17:00:00Z",
        "d": "Our hometown often harbors trauma that can stain the good memories we have. But coming to terms with where we come from and what shaped us allows for a certain peace and comfort that I believe only exists when we come back home. \nI’ve selected these sounds that portray the small town in Portugal where I was raised in. Hope I can take you there with me.",
        "j": null,
        "u": "https://www.nts.live/api/v2/shows/peace-2025/episodes/peace-2025-aldeia-portuguesa-w-henrique-2nd-january-2026"
      },
      {
        "n": "bring me to w/ helennaaa",
        "s": "2026-01-02T17:00:00Z",
        "e": "2026-01-02T18:00:00Z",
        "d": "gently flirting across time and genre, tune in and come down from the chaos with this mix of soul-soothing gems, both familiar and hidden.",
        "j": null,
        "u": "https://www.nts.live/api/v2/shows/peace-2025/episodes/peace-2025-bring-me-to-w-helennaaa-2nd-january-2026"
      },
      {
        "n": "STATIC DRIFT W/ FOA",
        "s": "2026-01-02T18:00:00Z",
        "e": "2026-01-02T19:00:00Z",
        "d": "60 minute decompression soundtrack, for blurring realms, for transcending consciousness. Organic and electronic music from all corners of the world, from the last 6 decades, unified by the resonance of twilight. Tracing the vibration from ritual gong music through to Popol Vuh to Autechre.",
        "j": null,
        "u": "https://www.nts.live/api/v2/shows/peace-2025/episodes/peace-2025-static-drift-w-foa-2nd-january-2026"
      },
      {
        "n": "Rhythms of Resistance, Songs of Peace w/ Afrodesi",
        "s": "2026-01-02T19:00:00Z",
        "e": "2026-01-02T20:00:00Z",
        "d": "A quest for peace through rhythms of resistance and songs of love. Weaving Afrofunk and Vodun grooves of defiance with griot wisdom and the hues of Bollywood love, this mix is guided by the belief that freedom, justice, love, and faith form the roots of peace — at once a political statement and a deeply personal reflection.",
        "j": null,
        "u": "https://www.nts.live/api/v2/shows/peace-2025/episodes/peace-2025-rhythms-of-resistance-songs-of-peace-w-afrodesi-2nd-january-2026"
      },
      {
        "n": "ACCEPTED VULNERABILITY W/ BROOCE",
        "s": "2026-01-02T20:00:00Z",
        "e": "2026-01-02T21:00:00Z",
        "d": "Peace for me has recently been a cross between accountability and vulnerability. Understanding the need for taking ownership of things you do, but also having the ability to be open to your emotions and experiences. So please enjoy my openness :)",
        "j": null,
        "u": "https://www.nts.live/api/v2/shows/peace-2025/episodes/peace-2025-accepted-vulnerability-w-brooce-2nd-january-2026"
      },
      {
        "n": "Harmonic Bliss w/ Angelo & Gracia",
        "s": "2026-01-02T21:00:00Z",
        "e": "2026-01-02T22:00:00Z",
        "d": "Attune to the emancipatory potential of bliss. Kaleidoscopic opportunities. Mystical sound waves. When is your time to flower?",
        "j": null,
        "u": "https://www.nts.live/api/v2/shows/peace-2025/episodes/peace-2025-harmonic-bliss-w-angelo-gracia-2nd-january-2026"
      },
      {
        "n": "GARDEN OF SUBLIMITY W/ DRYAKOBY",
        "s": "2026-01-02T22:00:00Z",
        "e": "2026-01-02T23:00:00Z",
        "d": "This is a collection of songs and field recordings cultivated among the flowers and vegetables in my garden this year, and it's all for you. I hope you enjoy it.",
        "j": null,
        "u": "https://www.nts.live/api/v2/shows/peace-2025/episodes/peace-2025-garden-of-sublimity-w-dryakoby-2nd-january-2026"
      },
      {
        "n": "INNER PEACE W/ TYLER ANDREW",
        "s": "2026-01-02T23:00:00Z",
        "e": "2026-01-03T00:00:00Z",
        "d": "This is mix of tracks that make it easier for me to feel at peace when the world around me feels like it isn't.",
        "j": null,
        "u": "https://www.nts.live/api/v2/shows/peace-2025/episodes/peace-2025-inner-peace-w-tyler-andrew-2nd-january-2026"
      },
      {
        "n": "PEACE MIX w/ ABSENT LANGUAGE",
        "s": "2026-01-03T00:00:00Z",
        "e": "2026-01-03T01:00:00Z",
        "d": null,
        "j": null,
        "u": null
      },
      {
        "n": "BETWEEN NOTHING AND NOISE w/ JAKOB DROZD",
        "s": "2026-01-03T01:00:00Z",
        "e": "2026-01-03T02:00:00Z",
        "d": "Tranquil soundscapes and fuzzy tones. The dichotomy of sound is proof that peace is something found at home.",
        "j": null,
        "u": "https://www.nts.live/api/v2/shows/peace-2025/episodes/peace-2025-between-nothing-and-noise-w-jakob-drozd-3rd-january-2026"
      },
      {
        "n": "sweetpea w/ ben ry",
        "s": "2026-01-03T02:00:00Z",
        "e": "2026-01-03T03:00:00Z",
        "d": "quiet moments, bliss, ease, memory\nshowing gratitude for the little things and keeping in mind that theres still a chance for peace. some things are worth fighting for! gotta remember that. these songs make me keep going.",
        "j": null,
        "u": "https://www.nts.live/api/v2/shows/peace-2025/episodes/peace-2025-sweetpea-w-ben-ry-3rd-january-2026"
      },
      {
        "n": "WHEN THE SKY WAS WHOLE W/ SLUMP",
        "s": "2026-01-03T03:00:00Z",
        "e": "2026-01-03T04:00:00Z",
        "d": "Slower jams and B-Sides. Sauntering across the landscape.",
        "j": null,
        "u": "https://www.nts.live/api/v2/shows/peace-2025/episodes/peace-2025-when-the-sky-was-whole-w-slump-3rd-january-2026"
      },
      {
        "n": "Each and Every Life",
        "s": "2026-01-03T04:00:00Z",
        "e": "2026-01-03T05:00:00Z",
        "d": "Everyone knows peace when they feel it: harmony, tranquility, love. But getting there can take work. That means care and respect for others, a lot of fearlessness, even some self-sacrifice. Done right, though, it’s a labor of joy. Because all life is precious (ignore the haters), and because together we will win.",
        "j": null,
        "u": "https://www.nts.live/api/v2/shows/peace-2025/episodes/peace-2025-each-and-every-life-3rd-january-2026"
      },
      {
        "n": "The weight of dust w/ auds",
        "s": "2026-01-03T05:00:00Z",
        "e": "2026-01-03T06:00:00Z",
        "d": null,
        "j": null,
        "u": null
      },
      {
        "n": "REST YOUR WINGS W/ GUULEED",
        "s": "2026-01-03T06:00:00Z",
        "e": "2026-01-03T07:00:00Z",
        "d": null,
        "j": null,
        "u": null
      },
      {
        "n": "peace piece",
        "s": "2026-01-03T07:00:00Z",
        "e": "2026-01-03T08:00:00Z",
        "d": null,
        "j": null,
        "u": null
      },
      {
        "n": "Raw Kernels w/ TwoFace",
        "s": "2026-01-03T08:00:00Z",
        "e": "2026-01-03T09:00:00Z",
        "d": null,
        "j": null,
        "u": null
      },
      {
        "n": "We Sing Together to Keep Ourselves Warm W/ Splendore",
        "s": "2026-01-03T09:00:00Z",
        "e": "2026-01-03T10:00:00Z",
        "d": null,
        "j": null,
        "u": null
      },
      {
        "n": "inner|outer W/ J.EX",
        "s": "2026-01-03T10:00:00Z",
        "e": "2026-01-03T11:00:00Z",
        "d": null,
        "j": null,
        "u": null
      },
      {
        "n": "SERENITY IN REFLECTION W/ PEACEKEEPER RADIO",
        "s": "2026-01-03T11:00:00Z",
        "e": "2026-01-03T12:00:00Z",
        "d": null,
        "j": null,
        "u": null
      },
      {
        "n": "Sonic Afterlife w/ Conduct Disorder",
        "s": "2026-01-03T12:00:00Z",
        "e": "2026-01-03T13:00:00Z",
        "d": null,
        "j": null,
        "u": null
      },
      {
        "n": "ZAMAN ZAMAN W/ SEDA MIMAROĞLU",
        "s": "2026-01-03T13:00:00Z",
        "e": "2026-01-03T14:00:00Z",
        "d": null,
        "j": null,
        "u": null
      },
      {
        "n": "HEARING VOICES W/ SANDRO MARAVILLAS",
        "s": "2026-01-03T14:00:00Z",
        "e": "2026-01-03T15:00:00Z",
        "d": null,
        "j": null,
        "u": null
      },
      {
        "n": "SOFT HORIZONS W/ CLASSIC MODE",
        "s": "2026-01-03T15:00:00Z",
        "e": "2026-01-03T16:00:00Z",
        "d": null,
        "j": null,
        "u": null
      },
      {
        "n": "HISTORICAL CONSCIOUSNESS W/ CALEB'S CURTAINS",
        "s": "2026-01-03T16:00:00Z",
        "e": "2026-01-03T17:00:00Z",
        "d": null,
        "j": null,
        "u": null
      },
      {
        "n": "Rebajada For Dawn W/ Puma",
        "s": "2026-01-03T17:00:00Z",
        "e": "2026-01-03T18:00:00Z",
        "d": null,
        "j": null,
        "u": null
      },
      {
        "n": "PEACE PIECE W/ SOFIA DE AFRICA",
        "s": "2026-01-03T18:00:00Z",
        "e": "2026-01-03T19:00:00Z",
        "d": null,
        "j": null,
        "u": null
      },
      {
        "n": "REST IN PEACE W/ SIDHARTTA TALUKDAR",
        "s": "2026-01-03T19:00:00Z",
        "e": "2026-01-03T20:00:00Z",
        "d": null,
        "j": null,
        "u": null
      },
      {
        "n": "3am w/ Scam Regrets",
        "s": "2026-01-03T20:00:00Z",
        "e": "2026-01-03T21:00:00Z",
        "d": null,
        "j": null,
        "u": null
      }
    ],
    "subtle": [
      {
        "n": " Collider",
        "s": "2026-01-02T15:00:00Z",
        "e": "2026-01-02T16:00:00Z",
        "d": null,
        "j": null,
        "u": null,
        "t": "monthly"
      },
      {
        "n": " Submundo Soundsystem",
        "s": "2026-01-02T16:00:00Z",
        "e": "2026-01-02T17:00:00Z",
        "d": null,
        "j": null,
        "u": null,
        "t": "monthly"
      },
      {
        "n": "Subtle Selects",
        "s": "2026-01-02T17:00:00Z",
        "e": "2026-01-02T18:00:00Z",
        "d": null,
        "j": null,
        "u": null,
        "t": "playlist"
      },
      {
        "n": "TILDA",
        "s": "2026-01-02T18:00:00Z",
        "e": "2026-01-02T19:00:00Z",
        "d": "DJ and radio producer TILDA will be live from the studio to kick off your weekend. She’ll cover all corners of electronic music as well as showcasing unmissable new tracks & chatting about motives for the weekend. \r\n\r\nEach month TILDA will be closing the show with a signature mix.",
        "j": null,
        "u": null,
        "t": "monthly"
      },
      {
        "n": "DJ Squarewave",
        "s": "2026-01-02T19:00:00Z",
        "e": "2026-01-02T20:00:00Z",
        "d": null,
        "j": null,
        "u": null,
        "t": "monthly"
      },
      {
        "n": "ON ROAD",
        "s": "2026-01-02T20:00:00Z",
        "e": "2026-01-02T21:00:00Z",
        "d": null,
        "j": null,
        "u": null,
        "t": "monthly"
      },
      {
        "n": "Judder Show",
        "s": "2026-01-02T21:00:00Z",
        "e": "2026-01-02T22:00:00Z",
        "d": null,
        "j": null,
        "u": null,
        "t": "weekly"
      },
      {
        "n": " Fuuki Fam",
        "s": "2026-01-02T22:00:00Z",
        "e": "2026-01-03T00:00:00Z",
        "d": null,
        "j": null,
        "u": null,
        "t": "monthly"
      },
      {
        "n": "Programm Ldn",
        "s": "2026-01-03T00:00:00Z",
        "e": "2026-01-03T02:00:00Z",
        "d": null,
        "j": null,
        "u": null,
        "t": "monthly"
      },
      {
        "n": "RHOMBI",
        "s": "2026-01-03T02:00:00Z",
        "e": "2026-01-03T03:00:00Z",
        "d": null,
        "j": null,
        "u": null,
        "t": "monthly"
      },
      {
        "n": "Subtle Selects",
        "s": "2026-01-03T03:00:00Z",
        "e": "2026-01-03T05:00:00Z",
        "d": null,
        "j": null,
        "u": null,
        "t": "playlist"
      },
      {
        "n": "Minus - Flow State",
        "s": "2026-01-03T05:00:00Z",
        "e": "2026-01-03T06:00:00Z",
        "d": null,
        "j": "Flow State",
        "u": null,
        "t": "weekly"
      },
      {
        "n": "La Sopa Demoniaca ",
        "s": "2026-01-03T09:00:00Z",
        "e": "2026-01-03T10:00:00Z",
        "d": null,
        "j": null,
        "u": null,
        "t": "monthly"
      },
      {
        "n": "Matty Banton - Roots & Dubs",
        "s": "2026-01-03T11:00:00Z",
        "e": "2026-01-03T12:00:00Z",
        "d": null,
        "j": "Roots & Dubs",
        "u": null,
        "t": "monthly"
      },
      {
        "n": "Live & Direct w/ Hannah",
        "s": "2026-01-03T13:00:00Z",
        "e": "2026-01-03T14:00:00Z",
        "d": "Live & Direct is the show that promises to make you dance and make you laugh, with your fave tunes that make you go 'Rahhh ain't hear this in time' and all the cheesy jokes from me, Hannah :) Lock in for the sickest guests and the most relatable stories about daily slips and hilarious situations I find myself in.",
        "j": "Hannah",
        "u": "https://www.subtleradio.com/artists/live-direct-w-hannah/",
        "t": "biweekly"
      },
      {
        "n": "soltura",
        "s": "2026-01-03T14:00:00Z",
        "e": "2026-01-03T16:00:00Z",
        "d": null,
        "j": null,
        "u": null,
        "t": "monthly"
      },
      {
        "n": "Big Kani presents Large Language",
        "s": "2026-01-03T16:00:00Z",
        "e": "2026-01-03T17:00:00Z",
        "d": null,
        "j": null,
        "u": null,
        "t": "monthly"
      },
      {
        "n": "Jon1st",
        "s": "2026-01-03T17:00:00Z",
        "e": "2026-01-03T18:00:00Z",
        "d": "Following his widely acclaimed breakout moment winning the 2013 DMC World Online Championships, Jon1st quickly built an international reputation as a ‘DJ’s DJ’. Not only proving himself as one of the world’s most diverse and musical turntablists, Jon also established himself as an on the pulse club DJ mixing across the alternative bass music spectrum and as an in demand live performer around the world, as well as recording acclaimed guest mixes for everyone from DJ Mag to Boiler Room to Ninja Tune’s Solid Steel to Mary Anne Hobbs to Keep Hush.",
        "j": null,
        "u": null,
        "t": "monthly"
      },
      {
        "n": "BAGGA BADNIS w/ Joe Joiner",
        "s": "2026-01-03T18:00:00Z",
        "e": "2026-01-03T20:00:00Z",
        "d": null,
        "j": "Joe Joiner",
        "u": null,
        "t": "monthly"
      },
      {
        "n": "Minus - Flow State",
        "s": "2026-01-03T21:00:00Z",
        "e": "2026-01-03T23:00:00Z",
        "d": null,
        "j": "Flow State",
        "u": null,
        "t": "weekly"
      },
      {
        "n": "seiko",
        "s": "2026-01-03T23:00:00Z",
        "e": "2026-01-04T00:00:00Z",
        "d": null,
        "j": null,
        "u": null,
        "t": "monthly"
      },
      {
        "n": "Dread or Dead Records",
        "s": "2026-01-04T00:00:00Z",
        "e": "2026-01-04T01:00:00Z",
        "d": null,
        "j": null,
        "u": null,
        "t": "monthly"
      },
      {
        "n": "1V",
        "s": "2026-01-04T01:00:00Z",
        "e": "2026-01-04T02:00:00Z",
        "d": null,
        "j": null,
        "u": null,
        "t": "monthly"
      },
      {
        "n": "Polar Dance w/Winter Games",
        "s": "2026-01-04T02:00:00Z",
        "e": "2026-01-04T03:00:00Z",
        "d": null,
        "j": null,
        "u": null,
        "t": "monthly"
      },
      {
        "n": "wañuy",
        "s": "2026-01-04T05:00:00Z",
        "e": "2026-01-04T06:00:00Z",
        "d": null,
        "j": null,
        "u": null,
        "t": "monthly"
      },
      {
        "n": "Cold Hippie",
        "s": "2026-01-04T08:00:00Z",
        "e": "2026-01-04T09:00:00Z",
        "d": null,
        "j": null,
        "u": null,
        "t": "monthly"
      },
      {
        "n": "First Press w/ Passo Passo",
        "s": "2026-01-04T09:00:00Z",
        "e": "2026-01-04T10:00:00Z",
        "d": null,
        "j": "Passo Passo",
        "u": null,
        "t": "monthly"
      },
      {
        "n": " Harbee",
        "s": "2026-01-04T10:00:00Z",
        "e": "2026-01-04T11:00:00Z",
        "d": null,
        "j": null,
        "u": null,
        "t": "monthly"
      },
      {
        "n": "Mood Shift w/ ANIKA",
        "s": "2026-01-04T11:00:00Z",
        "e": "2026-01-04T12:00:00Z",
        "d": null,
        "j": "ANIKA",
        "u": null,
        "t": "monthly"
      },
      {
        "n": "TAMA",
        "s": "2026-01-04T12:00:00Z",
        "e": "2026-01-04T13:00:00Z",
        "d": null,
        "j": null,
        "u": null,
        "t": "monthly"
      },
      {
        "n": "Aloona",
        "s": "2026-01-04T13:00:00Z",
        "e": "2026-01-04T14:00:00Z",
        "d": null,
        "j": null,
        "u": null,
        "t": "monthly"
      },
      {
        "n": "Robeare",
        "s": "2026-01-04T14:00:00Z",
        "e": "2026-01-04T15:00:00Z",
        "d": null,
        "j": null,
        "u": null,
        "t": "monthly"
      },
      {
        "n": "ExtraSauce w/ eatmybeat",
        "s": "2026-01-04T15:00:00Z",
        "e": "2026-01-04T17:00:00Z",
        "d": "Established in 2013, eatmybeat is a hybrid record label & club brand that was brought together by a group of friends with a passion for electronic music and building community. With diverse tastes, they support and champion the underground bass music scene through events and releases on the label. Refusing to be pigeonholed into a specific sound, they showcase everything from hip-hop, bass & breaks, through to techno, jungle, dubstep and grime. As long as it's tasty and full fat, you best believe eatmybeat are snacking on it.",
        "j": "eatmybeat",
        "u": "https://www.subtleradio.com/artists/extrasaus-w-eatmybeat/",
        "t": "monthly"
      },
      {
        "n": "Kitschko",
        "s": "2026-01-04T21:00:00Z",
        "e": "2026-01-04T22:00:00Z",
        "d": "Born in Sunderland, based in London, Kitschko's productions and selections display a deep appreciation of UK club culture, and an affinity for late night, introspective sounds.",
        "j": null,
        "u": null,
        "t": "monthly"
      },
      {
        "n": "Envelop",
        "s": "2026-01-04T22:00:00Z",
        "e": "2026-01-04T23:00:00Z",
        "d": null,
        "j": null,
        "u": null,
        "t": "monthly"
      },
      {
        "n": "Chacho",
        "s": "2026-01-04T23:00:00Z",
        "e": "2026-01-05T00:00:00Z",
        "d": "As a drummer since childhood, Chacho has always had an insatiable appetite for new and unique beats.\r\nCombining his love of global percussion, dark grooves and deeper low end frequencies, \r\nhis sets feature a blend of dubstep, grime, garage, breaks, hip hop and other flavours from around the world.",
        "j": null,
        "u": null,
        "t": "monthly"
      },
      {
        "n": "Bassment Sessions W/ CORD",
        "s": "2026-01-05T00:00:00Z",
        "e": "2026-01-05T01:00:00Z",
        "d": null,
        "j": "CORD",
        "u": null,
        "t": "monthly"
      },
      {
        "n": "Fome",
        "s": "2026-01-05T01:00:00Z",
        "e": "2026-01-05T02:00:00Z",
        "d": null,
        "j": null,
        "u": null,
        "t": "monthly"
      },
      {
        "n": "kstrobez",
        "s": "2026-01-05T02:00:00Z",
        "e": "2026-01-05T03:00:00Z",
        "d": null,
        "j": null,
        "u": null,
        "t": "monthly"
      },
      {
        "n": "Sacha Kassy",
        "s": "2026-01-05T05:00:00Z",
        "e": "2026-01-05T06:00:00Z",
        "d": null,
        "j": null,
        "u": null,
        "t": "monthly"
      },
      {
        "n": "Takydon",
        "s": "2026-01-05T06:00:00Z",
        "e": "2026-01-05T07:00:00Z",
        "d": null,
        "j": null,
        "u": null,
        "t": "monthly"
      },
      {
        "n": "VITRINE by Sasoun",
        "s": "2026-01-05T07:00:00Z",
        "e": "2026-01-05T08:00:00Z",
        "d": null,
        "j": null,
        "u": null,
        "t": "monthly"
      },
      {
        "n": " Hello, You’ve Reached The Grooveline",
        "s": "2026-01-05T08:00:00Z",
        "e": "2026-01-05T09:00:00Z",
        "d": null,
        "j": null,
        "u": null
      },
      {
        "n": "Lugovskiy",
        "s": "2026-01-05T09:00:00Z",
        "e": "2026-01-05T10:00:00Z",
        "d": null,
        "j": null,
        "u": null,
        "t": "monthly"
      },
      {
        "n": " Afro-Elected w/ IXYALA",
        "s": "2026-01-05T12:00:00Z",
        "e": "2026-01-05T13:00:00Z",
        "d": null,
        "j": "IXYALA",
        "u": null,
        "t": "monthly"
      },
      {
        "n": "DINNERPLATEZ w/ KRETEKBOYZ ",
        "s": "2026-01-05T13:00:00Z",
        "e": "2026-01-05T14:00:00Z",
        "d": null,
        "j": "KRETEKBOYZ",
        "u": null,
        "t": "monthly"
      },
      {
        "n": "Enable",
        "s": "2026-01-05T14:00:00Z",
        "e": "2026-01-05T15:00:00Z",
        "d": null,
        "j": null,
        "u": null,
        "t": "monthly"
      },
      {
        "n": "L!pi",
        "s": "2026-01-05T15:00:00Z",
        "e": "2026-01-05T16:00:00Z",
        "d": null,
        "j": null,
        "u": null,
        "t": "monthly"
      },
      {
        "n": "Strange Signals",
        "s": "2026-01-05T16:00:00Z",
        "e": "2026-01-05T17:00:00Z",
        "d": null,
        "j": null,
        "u": null,
        "t": "monthly"
      },
      {
        "n": "Drumphill",
        "s": "2026-01-05T17:00:00Z",
        "e": "2026-01-05T18:00:00Z",
        "d": null,
        "j": null,
        "u": null,
        "t": "monthly"
      },
      {
        "n": "Underground Credentials",
        "s": "2026-01-05T18:00:00Z",
        "e": "2026-01-05T19:00:00Z",
        "d": null,
        "j": null,
        "u": null,
        "t": "monthly"
      },
      {
        "n": "glosssd",
        "s": "2026-01-05T19:00:00Z",
        "e": "2026-01-05T20:00:00Z",
        "d": null,
        "j": null,
        "u": null,
        "t": "monthly"
      },
      {
        "n": "JDubz",
        "s": "2026-01-05T20:00:00Z",
        "e": "2026-01-05T21:00:00Z",
        "d": null,
        "j": null,
        "u": null,
        "t": "monthly"
      },
      {
        "n": "Polo Jaffa",
        "s": "2026-01-05T21:00:00Z",
        "e": "2026-01-05T22:00:00Z",
        "d": null,
        "j": null,
        "u": null,
        "t": "monthly"
      },
      {
        "n": "LATO",
        "s": "2026-01-05T22:00:00Z",
        "e": "2026-01-05T23:00:00Z",
        "d": null,
        "j": null,
        "u": null,
        "t": "monthly"
      },
      {
        "n": "Baxter",
        "s": "2026-01-05T23:00:00Z",
        "e": "2026-01-06T00:00:00Z",
        "d": null,
        "j": null,
        "u": null,
        "t": "monthly"
      },
      {
        "n": "Dr.Velodrome",
        "s": "2026-01-06T00:00:00Z",
        "e": "2026-01-06T01:00:00Z",
        "d": null,
        "j": null,
        "u": null
      },
      {
        "n": "X-Pert Pir",
        "s": "2026-01-06T01:00:00Z",
        "e": "2026-01-06T02:00:00Z",
        "d": null,
        "j": null,
        "u": null,
        "t": "monthly"
      },
      {
        "n": "Underscore_",
        "s": "2026-01-06T02:00:00Z",
        "e": "2026-01-06T03:00:00Z",
        "d": null,
        "j": null,
        "u": null,
        "t": "monthly"
      },
      {
        "n": "Cartwright ",
        "s": "2026-01-06T05:00:00Z",
        "e": "2026-01-06T06:00:00Z",
        "d": null,
        "j": null,
        "u": null,
        "t": "monthly"
      },
      {
        "n": " Bristalo w/ Indiescotheque",
        "s": "2026-01-06T07:00:00Z",
        "e": "2026-01-06T08:00:00Z",
        "d": null,
        "j": null,
        "u": null
      },
      {
        "n": "Xanadu w/ Xanthe",
        "s": "2026-01-06T08:00:00Z",
        "e": "2026-01-06T09:00:00Z",
        "d": null,
        "j": "Xanthe",
        "u": null,
        "t": "monthly"
      },
      {
        "n": "TorbM",
        "s": "2026-01-06T09:00:00Z",
        "e": "2026-01-06T10:00:00Z",
        "d": null,
        "j": null,
        "u": null,
        "t": "monthly"
      },
      {
        "n": "Leiiila",
        "s": "2026-01-06T10:00:00Z",
        "e": "2026-01-06T11:00:00Z",
        "d": null,
        "j": null,
        "u": null,
        "t": "monthly"
      },
      {
        "n": "Octoroots",
        "s": "2026-01-06T11:00:00Z",
        "e": "2026-01-06T12:00:00Z",
        "d": null,
        "j": null,
        "u": null,
        "t": "monthly"
      },
      {
        "n": "Jakesy",
        "s": "2026-01-06T12:00:00Z",
        "e": "2026-01-06T13:00:00Z",
        "d": null,
        "j": null,
        "u": null,
        "t": "monthly"
      },
      {
        "n": "Bass Exchange",
        "s": "2026-01-06T13:00:00Z",
        "e": "2026-01-06T14:00:00Z",
        "d": null,
        "j": null,
        "u": null,
        "t": "monthly"
      },
      {
        "n": "Solly",
        "s": "2026-01-06T14:00:00Z",
        "e": "2026-01-06T15:00:00Z",
        "d": null,
        "j": null,
        "u": null,
        "t": "monthly"
      },
      {
        "n": "Nicked Fawlty",
        "s": "2026-01-06T15:00:00Z",
        "e": "2026-01-06T16:00:00Z",
        "d": null,
        "j": null,
        "u": null,
        "t": "monthly"
      },
      {
        "n": "Get On festival ",
        "s": "2026-01-06T16:00:00Z",
        "e": "2026-01-06T17:00:00Z",
        "d": null,
        "j": null,
        "u": null,
        "t": "monthly"
      },
      {
        "n": " Karishma",
        "s": "2026-01-06T18:00:00Z",
        "e": "2026-01-06T19:00:00Z",
        "d": null,
        "j": null,
        "u": null,
        "t": "biweekly"
      },
      {
        "n": "Ro-Motion",
        "s": "2026-01-06T19:00:00Z",
        "e": "2026-01-06T20:00:00Z",
        "d": null,
        "j": null,
        "u": null,
        "t": "monthly"
      },
      {
        "n": "Jake Plisken",
        "s": "2026-01-06T20:00:00Z",
        "e": "2026-01-06T22:00:00Z",
        "d": null,
        "j": null,
        "u": null
      },
      {
        "n": "Slow Process w/ Ufaze",
        "s": "2026-01-06T22:00:00Z",
        "e": "2026-01-06T23:00:00Z",
        "d": null,
        "j": "Ufaze",
        "u": null,
        "t": "monthly"
      },
      {
        "n": "Minuscule Music Show with Bondy",
        "s": "2026-01-06T23:00:00Z",
        "e": "2026-01-07T00:00:00Z",
        "d": null,
        "j": null,
        "u": null,
        "t": "monthly"
      },
      {
        "n": "KUBA KONOFALSKI",
        "s": "2026-01-07T00:00:00Z",
        "e": "2026-01-07T02:00:00Z",
        "d": null,
        "j": null,
        "u": null,
        "t": "monthly"
      },
      {
        "n": "Shreztah Selects",
        "s": "2026-01-07T02:00:00Z",
        "e": "2026-01-07T03:00:00Z",
        "d": null,
        "j": null,
        "u": null,
        "t": "monthly"
      },
      {
        "n": "NOS-talgia",
        "s": "2026-01-07T03:00:00Z",
        "e": "2026-01-07T04:00:00Z",
        "d": null,
        "j": null,
        "u": null,
        "t": "monthly"
      },
      {
        "n": "Step Inside w/ ZAAGO",
        "s": "2026-01-07T04:00:00Z",
        "e": "2026-01-07T05:00:00Z",
        "d": null,
        "j": "ZAAGO",
        "u": null,
        "t": "monthly"
      },
      {
        "n": "cayel",
        "s": "2026-01-07T05:00:00Z",
        "e": "2026-01-07T06:00:00Z",
        "d": null,
        "j": null,
        "u": null,
        "t": "monthly"
      },
      {
        "n": "Sing/Say w/ Paul Hertmann",
        "s": "2026-01-07T08:00:00Z",
        "e": "2026-01-07T09:00:00Z",
        "d": null,
        "j": "Paul Hertmann",
        "u": null,
        "t": "monthly"
      },
      {
        "n": "Music that Moves",
        "s": "2026-01-07T10:00:00Z",
        "e": "2026-01-07T11:00:00Z",
        "d": null,
        "j": null,
        "u": null,
        "t": "monthly"
      },
      {
        "n": "Nikki O",
        "s": "2026-01-07T11:00:00Z",
        "e": "2026-01-07T12:00:00Z",
        "d": "Hailing from Belfast but making moves in Nottingham, Nikki O is a DJ and radio presenter whose sets blend 4/4 rhythms, breakbeats, and the bassier side of techno. ",
        "j": null,
        "u": null,
        "t": "biweekly"
      },
      {
        "n": "PAVZKY",
        "s": "2026-01-07T12:00:00Z",
        "e": "2026-01-07T13:00:00Z",
        "d": null,
        "j": null,
        "u": null,
        "t": "monthly"
      },
      {
        "n": "Live Laugh Layla",
        "s": "2026-01-07T13:00:00Z",
        "e": "2026-01-07T14:00:00Z",
        "d": null,
        "j": null,
        "u": null,
        "t": "monthly"
      },
      {
        "n": "IC FM w/ Luke Ferrero",
        "s": "2026-01-07T15:00:00Z",
        "e": "2026-01-07T16:00:00Z",
        "d": null,
        "j": "Luke Ferrero",
        "u": null,
        "t": "monthly"
      },
      {
        "n": "Sonic Seasoning ",
        "s": "2026-01-07T16:00:00Z",
        "e": "2026-01-07T17:00:00Z",
        "d": null,
        "j": null,
        "u": null,
        "t": "monthly"
      },
      {
        "n": "Groundwrk w/ B4B",
        "s": "2026-01-07T17:00:00Z",
        "e": "2026-01-07T18:00:00Z",
        "d": null,
        "j": "B4B",
        "u": null,
        "t": "monthly"
      },
      {
        "n": " Ellen",
        "s": "2026-01-07T18:00:00Z",
        "e": "2026-01-07T19:00:00Z",
        "d": null,
        "j": null,
        "u": null,
        "t": "monthly"
      },
      {
        "n": "Murky Sonics",
        "s": "2026-01-07T19:00:00Z",
        "e": "2026-01-07T20:00:00Z",
        "d": null,
        "j": null,
        "u": null,
        "t": "monthly"
      },
      {
        "n": " INDXSTRIAL STRXNGTH",
        "s": "2026-01-07T20:00:00Z",
        "e": "2026-01-07T21:00:00Z",
        "d": null,
        "j": null,
        "u": null,
        "t": "monthly"
      },
      {
        "n": "Seshington",
        "s": "2026-01-07T21:00:00Z",
        "e": "2026-01-07T22:00:00Z",
        "d": null,
        "j": null,
        "u": null,
        "t": "monthly"
      },
      {
        "n": "PANACEA",
        "s": "2026-01-07T23:00:00Z",
        "e": "2026-01-08T00:00:00Z",
        "d": null,
        "j": null,
        "u": null,
        "t": "biweekly"
      },
      {
        "n": "Odds and Ends w/ Moon J",
        "s": "2026-01-08T00:00:00Z",
        "e": "2026-01-08T01:00:00Z",
        "d": null,
        "j": "Moon J",
        "u": null,
        "t": "monthly"
      },
      {
        "n": "The Dubversified Show",
        "s": "2026-01-08T01:00:00Z",
        "e": "2026-01-08T03:00:00Z",
        "d": "Dubversified showcases Canadian West Coast DJ talent specializing in Bass Music. Hosted by Mirage, founder of Dubversified Culture, a community-led organization focusing on music, art, and events. Mirage, originally from Québec, blends house and hip-hop since 2010, now exploring 140bpm and Deep D&B.",
        "j": null,
        "u": null,
        "t": "monthly"
      },
      {
        "n": "rowthedecks",
        "s": "2026-01-08T03:00:00Z",
        "e": "2026-01-08T04:00:00Z",
        "d": null,
        "j": null,
        "u": null,
        "t": "monthly"
      }
    ],
    "dublab": [
      {
        "n": "sounds of NOW",
        "s": "2026-01-02T14:00:00Z",
        "e": "2026-01-02T16:00:00Z",
        "d": null,
        "j": null,
        "u": null,
        "t": "playlist"
      },
      {
        "n": "sounds of NOW",
        "s": "2026-01-02T16:00:00Z",
        "e": "2026-01-02T18:00:00Z",
        "d": null,
        "j": null,
        "u": null,
        "t": "playlist"
      },
      {
        "n": "Daddy Differently and Dirty Dave - Things of Life",
        "s": "2026-01-02T18:00:00Z",
        "e": "2026-01-02T20:00:00Z",
        "d": "It’s the simple things isn’t it? The little things of life. Good food, sunshine, no traffic, dark coffee, 72˚ breeze, telephone off the hook and music every Friday morning a la Daddy Differently & Dirty Dave.",
        "j": "Things of Life",
        "u": null,
        "t": "weekly"
      },
      {
        "n": "Masha Mar – Analogue Players Club",
        "s": "2026-01-02T20:00:00Z",
        "e": "2026-01-02T22:00:00Z",
        "d": null,
        "j": null,
        "u": null,
        "t": "monthly"
      },
      {
        "n": "Secret Circuit - Cosmic Neighborhood",
        "s": "2026-01-02T22:00:00Z",
        "e": "2026-01-03T00:00:00Z",
        "d": null,
        "j": "Cosmic Neighborhood",
        "u": null,
        "t": "monthly"
      },
      {
        "n": "Dor Wand – Open Heart Social Club",
        "s": "2026-01-03T00:00:00Z",
        "e": "2026-01-03T02:00:00Z",
        "d": null,
        "j": null,
        "u": null,
        "t": "monthly"
      },
      {
        "n": "Jeffery Plansker - Jazz Advance",
        "s": "2026-01-03T02:00:00Z",
        "e": "2026-01-03T04:00:00Z",
        "d": null,
        "j": "Jazz Advance",
        "u": null,
        "t": "monthly"
      },
      {
        "n": "45 Live Radio Show",
        "s": "2026-01-03T04:00:00Z",
        "e": "2026-01-03T06:00:00Z",
        "d": null,
        "j": null,
        "u": null,
        "t": "monthly"
      },
      {
        "n": "Daniel Troberg - Transition",
        "s": "2026-01-03T06:00:00Z",
        "e": "2026-01-03T08:00:00Z",
        "d": null,
        "j": "Transition",
        "u": null,
        "t": "monthly"
      },
      {
        "n": "sounds of NOW",
        "s": "2026-01-03T08:00:00Z",
        "e": "2026-01-03T10:00:00Z",
        "d": null,
        "j": null,
        "u": null,
        "t": "playlist"
      },
      {
        "n": "sounds of NOW",
        "s": "2026-01-03T12:00:00Z",
        "e": "2026-01-03T14:00:00Z",
        "d": null,
        "j": null,
        "u": null,
        "t": "playlist"
      },
      {
        "n": "T-Kay - The Archive of Feelings",
        "s": "2026-01-03T18:00:00Z",
        "e": "2026-01-03T20:00:00Z",
        "d": null,
        "j": "The Archive of Feelings",
        "u": null,
        "t": "monthly"
      },
      {
        "n": "Time Away with Maral",
        "s": "2026-01-03T20:00:00Z",
        "e": "2026-01-03T22:00:00Z",
        "d": null,
        "j": null,
        "u": null,
        "t": "monthly"
      },
      {
        "n": "mmarz",
        "s": "2026-01-03T22:00:00Z",
        "e": "2026-01-04T00:00:00Z",
        "d": null,
        "j": null,
        "u": null,
        "t": "monthly"
      },
      {
        "n": "Callie Ryan - Storage Container",
        "s": "2026-01-04T00:00:00Z",
        "e": "2026-01-04T02:00:00Z",
        "d": null,
        "j": "Storage Container",
        "u": null,
        "t": "biweekly"
      },
      {
        "n": "Andy Oro and Akumen - Made to Move",
        "s": "2026-01-04T02:00:00Z",
        "e": "2026-01-04T04:00:00Z",
        "d": null,
        "j": "Made to Move",
        "u": null,
        "t": "monthly"
      },
      {
        "n": "Chico Sonido Mixxx Show",
        "s": "2026-01-04T04:00:00Z",
        "e": "2026-01-04T06:00:00Z",
        "d": null,
        "j": null,
        "u": null,
        "t": "monthly"
      },
      {
        "n": "Richard Fearless - Metal Box",
        "s": "2026-01-04T06:00:00Z",
        "e": "2026-01-04T08:00:00Z",
        "d": null,
        "j": "Metal Box",
        "u": null,
        "t": "monthly"
      },
      {
        "n": "djjs",
        "s": "2026-01-04T13:00:00Z",
        "e": "2026-01-04T15:00:00Z",
        "d": null,
        "j": null,
        "u": null,
        "t": "playlist"
      },
      {
        "n": "djjs 2",
        "s": "2026-01-04T15:00:00Z",
        "e": "2026-01-04T17:00:00Z",
        "d": null,
        "j": null,
        "u": null,
        "t": "playlist"
      },
      {
        "n": "Kenneth Bager - Music for Dreams",
        "s": "2026-01-04T17:00:00Z",
        "e": "2026-01-04T18:00:00Z",
        "d": null,
        "j": "Music for Dreams",
        "u": null,
        "t": "weekly"
      },
      {
        "n": "Chris Kissel and Chuck Soo-Hoo - Contact Wave",
        "s": "2026-01-04T18:00:00Z",
        "e": "2026-01-04T20:00:00Z",
        "d": null,
        "j": "Contact Wave",
        "u": null,
        "t": "monthly"
      },
      {
        "n": "Mary Nagakawa – Underscore",
        "s": "2026-01-04T20:00:00Z",
        "e": "2026-01-04T21:00:00Z",
        "d": null,
        "j": null,
        "u": null,
        "t": "monthly"
      },
      {
        "n": "Mas Exitos con Ganas",
        "s": "2026-01-04T22:00:00Z",
        "e": "2026-01-05T00:00:00Z",
        "d": null,
        "j": null,
        "u": null,
        "t": "monthly"
      },
      {
        "n": "Noir and Jae Drago - Juke Bounce Werk Radio",
        "s": "2026-01-05T00:00:00Z",
        "e": "2026-01-05T02:00:00Z",
        "d": null,
        "j": "Juke Bounce Werk Radio",
        "u": null,
        "t": "monthly"
      },
      {
        "n": "DJ TY - The Long Decay",
        "s": "2026-01-05T02:00:00Z",
        "e": "2026-01-05T04:00:00Z",
        "d": null,
        "j": "The Long Decay",
        "u": null,
        "t": "monthly"
      },
      {
        "n": "Canary Sound Werk",
        "s": "2026-01-05T04:00:00Z",
        "e": "2026-01-05T06:00:00Z",
        "d": null,
        "j": null,
        "u": null,
        "t": "monthly"
      },
      {
        "n": "Xen Model w/ pTR - Upload",
        "s": "2026-01-05T06:00:00Z",
        "e": "2026-01-05T08:00:00Z",
        "d": null,
        "j": "pTR",
        "u": null,
        "t": "monthly"
      },
      {
        "n": "Thalma de Freitas – THALMA PLAYS BRASIL",
        "s": "2026-01-05T16:00:00Z",
        "e": "2026-01-05T18:00:00Z",
        "d": null,
        "j": null,
        "u": null,
        "t": "monthly"
      },
      {
        "n": "Rene Contreras - Viva! Talks",
        "s": "2026-01-05T18:00:00Z",
        "e": "2026-01-05T20:00:00Z",
        "d": null,
        "j": "Viva! Talks",
        "u": null,
        "t": "weekly"
      },
      {
        "n": "LUPE - RECENTS",
        "s": "2026-01-05T20:00:00Z",
        "e": "2026-01-05T22:00:00Z",
        "d": null,
        "j": "RECENTS",
        "u": null,
        "t": "monthly"
      },
      {
        "n": "Beau Matthews - Urban Farmer Radio",
        "s": "2026-01-05T22:00:00Z",
        "e": "2026-01-06T00:00:00Z",
        "d": null,
        "j": "Urban Farmer Radio",
        "u": null,
        "t": "monthly"
      },
      {
        "n": "open slot",
        "s": "2026-01-06T00:00:00Z",
        "e": "2026-01-06T02:00:00Z",
        "d": null,
        "j": null,
        "u": null
      },
      {
        "n": "Ella Warren - Lucky Lefty",
        "s": "2026-01-06T01:55:00Z",
        "e": "2026-01-06T03:00:00Z",
        "d": null,
        "j": "Lucky Lefty",
        "u": null,
        "t": "monthly"
      },
      {
        "n": "Trovarsi - Signal",
        "s": "2026-01-06T03:00:00Z",
        "e": "2026-01-06T04:00:00Z",
        "d": null,
        "j": "Signal",
        "u": null,
        "t": "monthly"
      },
      {
        "n": "Monalisa Murray - Paths of Rhythm",
        "s": "2026-01-06T04:00:00Z",
        "e": "2026-01-06T06:00:00Z",
        "d": null,
        "j": "Paths of Rhythm",
        "u": null,
        "t": "monthly"
      },
      {
        "n": "Jenny NONO - SS Extension Course",
        "s": "2026-01-06T06:00:00Z",
        "e": "2026-01-06T08:00:00Z",
        "d": null,
        "j": "SS Extension Course",
        "u": null,
        "t": "monthly"
      },
      {
        "n": "Gulniyal - gtalks! radio",
        "s": "2026-01-06T16:00:00Z",
        "e": "2026-01-06T17:00:00Z",
        "d": null,
        "j": "gtalks! radio",
        "u": null,
        "t": "monthly"
      },
      {
        "n": "Chandler Poling - Studio Soundtracks",
        "s": "2026-01-06T17:00:00Z",
        "e": "2026-01-06T18:00:00Z",
        "d": null,
        "j": "Studio Soundtracks",
        "u": null,
        "t": "monthly"
      },
      {
        "n": "Jonathan Kornman - Discoteca Imaginaria",
        "s": "2026-01-06T18:00:00Z",
        "e": "2026-01-06T20:00:00Z",
        "d": null,
        "j": "Discoteca Imaginaria",
        "u": null,
        "t": "monthly"
      },
      {
        "n": "Teebs - Viewpoints",
        "s": "2026-01-06T20:00:00Z",
        "e": "2026-01-06T22:00:00Z",
        "d": null,
        "j": "Viewpoints",
        "u": null,
        "t": "monthly"
      },
      {
        "n": "Protect Me – PROPRO’s HIP-HOP PUNK HOUSE",
        "s": "2026-01-06T22:00:00Z",
        "e": "2026-01-07T00:00:00Z",
        "d": null,
        "j": null,
        "u": null
      },
      {
        "n": "Hoseh - Version Sounds",
        "s": "2026-01-07T00:00:00Z",
        "e": "2026-01-07T02:00:00Z",
        "d": null,
        "j": "Version Sounds",
        "u": null,
        "t": "weekly"
      },
      {
        "n": "Langosta y Miche – Sonámbula Radio",
        "s": "2026-01-07T02:00:00Z",
        "e": "2026-01-07T04:00:00Z",
        "d": null,
        "j": null,
        "u": null,
        "t": "monthly"
      },
      {
        "n": "Echo Park Film Center - Optical Track",
        "s": "2026-01-07T04:00:00Z",
        "e": "2026-01-07T06:00:00Z",
        "d": null,
        "j": "Optical Track",
        "u": null,
        "t": "weekly"
      },
      {
        "n": "Kaustin - Subsurface Radio",
        "s": "2026-01-07T06:00:00Z",
        "e": "2026-01-07T08:00:00Z",
        "d": null,
        "j": "Subsurface Radio",
        "u": null,
        "t": "monthly"
      },
      {
        "n": "in plain sight radio",
        "s": "2026-01-07T16:00:00Z",
        "e": "2026-01-07T18:00:00Z",
        "d": null,
        "j": null,
        "u": null,
        "t": "monthly"
      },
      {
        "n": "Andres Renteria - Shining Spirit Sound",
        "s": "2026-01-07T18:00:00Z",
        "e": "2026-01-07T20:00:00Z",
        "d": null,
        "j": "Shining Spirit Sound",
        "u": null,
        "t": "monthly"
      },
      {
        "n": "Lana Miller – Soft Focus",
        "s": "2026-01-07T21:00:00Z",
        "e": "2026-01-07T22:00:00Z",
        "d": null,
        "j": null,
        "u": null,
        "t": "monthly"
      },
      {
        "n": "Colored Craig - Club Craig",
        "s": "2026-01-07T22:00:00Z",
        "e": "2026-01-08T00:00:00Z",
        "d": null,
        "j": "Club Craig",
        "u": null,
        "t": "monthly"
      },
      {
        "n": "In Sheep's Clothing – World of Sound",
        "s": "2026-01-08T00:00:00Z",
        "e": "2026-01-08T02:00:00Z",
        "d": null,
        "j": null,
        "u": null,
        "t": "monthly"
      },
      {
        "n": "Kins – Footnote",
        "s": "2026-01-08T02:00:00Z",
        "e": "2026-01-08T04:00:00Z",
        "d": null,
        "j": null,
        "u": null,
        "t": "monthly"
      }
    ],
    "rinse": [
      {
        "n": "Patrick Hinton",
        "s": "2026-01-02T12:00:00Z",
        "e": "2026-01-02T18:00:00Z",
        "d": null,
        "j": "SHERELLE",
        "u": null,
        "t": "weekly"
      },
      {
        "n": "Jasper James",
        "s": "2026-01-02T14:00:00Z",
        "e": "2026-01-02T17:00:00Z",
        "d": null,
        "j": "B2B Carista",
        "u": null,
        "t": "biweekly"
      },
      {
        "n": "G33 B2B Saint Ludo",
        "s": "2026-01-02T17:00:00Z",
        "e": "2026-01-02T18:00:00Z",
        "d": null,
        "j": null,
        "u": null
      },
      {
        "n": "nora",
        "s": "2026-01-02T18:00:00Z",
        "e": "2026-01-02T19:00:00Z",
        "d": null,
        "j": "Ruby Jean Smith & Jinnal",
        "u": null,
        "t": "weekly"
      },
      {
        "n": "Borne Fruits with Amaliah",
        "s": "2026-01-02T19:00:00Z",
        "e": "2026-01-02T20:00:00Z",
        "d": null,
        "j": "100% Production Mix",
        "u": null
      },
      {
        "n": "Hessle Audio feat. Ben UFO",
        "s": "2026-01-02T20:00:00Z",
        "e": "2026-01-02T22:00:00Z",
        "d": null,
        "j": "Recorded At Sustain Release 2025",
        "u": null
      },
      {
        "n": "Nancy June B2B Mantra with SP:MC",
        "s": "2026-01-02T22:00:00Z",
        "e": "2026-01-02T23:00:00Z",
        "d": null,
        "j": null,
        "u": null
      },
      {
        "n": "Paranoid London",
        "s": "2026-01-02T23:00:00Z",
        "e": "2026-01-03T00:00:00Z",
        "d": null,
        "j": null,
        "u": null
      },
      {
        "n": "Pariah presents Voam",
        "s": "2026-01-03T00:00:00Z",
        "e": "2026-01-03T02:00:00Z",
        "d": null,
        "j": "mad miran",
        "u": null,
        "t": "biweekly"
      },
      {
        "n": "Playlist",
        "s": "2026-01-03T02:00:00Z",
        "e": "2026-01-03T06:00:00Z",
        "d": null,
        "j": null,
        "u": null,
        "t": "playlist"
      },
      {
        "n": "Playlist",
        "s": "2026-01-03T06:00:00Z",
        "e": "2026-01-03T09:00:00Z",
        "d": null,
        "j": null,
        "u": null,
        "t": "playlist"
      },
      {
        "n": "Esk",
        "s": "2026-01-03T09:00:00Z",
        "e": "2026-01-03T11:00:00Z",
        "d": null,
        "j": "EarthGang",
        "u": null,
        "t": "weekly"
      },
      {
        "n": "Cara Crosby",
        "s": "2026-01-03T11:00:00Z",
        "e": "2026-01-03T12:00:00Z",
        "d": null,
        "j": "The Apple in The Dark",
        "u": null,
        "t": "weekly"
      },
      {
        "n": "Patrick Hinton",
        "s": "2026-01-03T12:00:00Z",
        "e": "2026-01-03T18:00:00Z",
        "d": null,
        "j": "SHERELLE",
        "u": null,
        "t": "weekly"
      },
      {
        "n": "LILA",
        "s": "2026-01-03T18:00:00Z",
        "e": "2026-01-03T20:00:00Z",
        "d": null,
        "j": "JJAMZ",
        "u": null,
        "t": "biweekly"
      },
      {
        "n": "Main Phase",
        "s": "2026-01-03T20:00:00Z",
        "e": "2026-01-03T22:00:00Z",
        "d": null,
        "j": "140 Special",
        "u": null,
        "t": "weekly"
      },
      {
        "n": "1985 Music",
        "s": "2026-01-03T22:00:00Z",
        "e": "2026-01-03T23:00:00Z",
        "d": null,
        "j": "Alix Perez",
        "u": null
      },
      {
        "n": "Surusinghe",
        "s": "2026-01-03T23:00:00Z",
        "e": "2026-01-04T00:00:00Z",
        "d": null,
        "j": "B2B Ma Sha B2B TSVI",
        "u": null,
        "t": "weekly"
      },
      {
        "n": "Ehua",
        "s": "2026-01-04T00:00:00Z",
        "e": "2026-01-04T01:00:00Z",
        "d": null,
        "j": null,
        "u": null,
        "t": "monthly"
      },
      {
        "n": "ryota",
        "s": "2026-01-04T01:00:00Z",
        "e": "2026-01-04T07:00:00Z",
        "d": null,
        "j": "Back to old school",
        "u": null,
        "t": "monthly"
      },
      {
        "n": "Playlist",
        "s": "2026-01-04T07:00:00Z",
        "e": "2026-01-04T09:00:00Z",
        "d": null,
        "j": null,
        "u": null,
        "t": "playlist"
      },
      {
        "n": "Wisdom Teeth",
        "s": "2026-01-04T09:00:00Z",
        "e": "2026-01-04T11:00:00Z",
        "d": null,
        "j": "Jorg Kuning",
        "u": null,
        "t": "biweekly"
      },
      {
        "n": "Camille Munn",
        "s": "2026-01-04T11:00:00Z",
        "e": "2026-01-04T12:00:00Z",
        "d": null,
        "j": "Intranet Girl & Jay-D",
        "u": null,
        "t": "biweekly"
      },
      {
        "n": "Elle Clark",
        "s": "2026-01-04T12:00:00Z",
        "e": "2026-01-04T14:00:00Z",
        "d": null,
        "j": "A Short History of Detroit Ghettotech",
        "u": null,
        "t": "monthly"
      },
      {
        "n": "Lady Passion",
        "s": "2026-01-04T14:00:00Z",
        "e": "2026-01-04T15:00:00Z",
        "d": null,
        "j": "The MoodSwing Takeover",
        "u": null
      },
      {
        "n": "Brighter Days Family",
        "s": "2026-01-04T15:00:00Z",
        "e": "2026-01-04T17:00:00Z",
        "d": null,
        "j": "Cuppa Sounds + Omeara Recap",
        "u": null,
        "t": "weekly"
      },
      {
        "n": "Storm Mollison",
        "s": "2026-01-04T17:00:00Z",
        "e": "2026-01-04T18:00:00Z",
        "d": null,
        "j": "Early 2000s Special",
        "u": null,
        "t": "biweekly"
      },
      {
        "n": "Oneman",
        "s": "2026-01-04T18:00:00Z",
        "e": "2026-01-04T20:00:00Z",
        "d": null,
        "j": null,
        "u": null,
        "t": "biweekly"
      },
      {
        "n": "RIZ LA TEEF",
        "s": "2026-01-04T20:00:00Z",
        "e": "2026-01-04T22:00:00Z",
        "d": null,
        "j": "B2B L-VIS 1990 W/ MISTA SILVA",
        "u": null
      },
      {
        "n": "Just Jane",
        "s": "2026-01-04T22:00:00Z",
        "e": "2026-01-04T23:00:00Z",
        "d": null,
        "j": "B2B Tim Reaper",
        "u": null,
        "t": "weekly"
      },
      {
        "n": "Zenker Brothers",
        "s": "2026-01-04T23:00:00Z",
        "e": "2026-01-05T00:00:00Z",
        "d": null,
        "j": null,
        "u": null
      }
    ],
    "rinsefr": [
      {
        "n": "Griffes d'Anges",
        "s": "2026-01-02T15:00:00Z",
        "e": "2026-01-02T16:00:00Z",
        "d": null,
        "j": null,
        "u": null,
        "t": "monthly"
      },
      {
        "n": "Sevenbeatz",
        "s": "2026-01-02T16:00:00Z",
        "e": "2026-01-02T17:00:00Z",
        "d": null,
        "j": "100% Garage House",
        "u": null
      },
      {
        "n": "RAAR",
        "s": "2026-01-02T17:00:00Z",
        "e": "2026-01-02T18:00:00Z",
        "d": null,
        "j": "new year, same flesh prison with LOUISAHHH",
        "u": null,
        "t": "monthly"
      },
      {
        "n": "Vanille",
        "s": "2026-01-02T18:00:00Z",
        "e": "2026-01-02T19:00:00Z",
        "d": null,
        "j": null,
        "u": null,
        "t": "monthly"
      },
      {
        "n": "Playlist France",
        "s": "2026-01-02T19:00:00Z",
        "e": "2026-01-02T23:00:00Z",
        "d": null,
        "j": null,
        "u": null,
        "t": "playlist"
      },
      {
        "n": "Playlist France",
        "s": "2026-01-02T23:00:00Z",
        "e": "2026-01-03T08:00:00Z",
        "d": null,
        "j": null,
        "u": null,
        "t": "playlist"
      },
      {
        "n": "Playlist France",
        "s": "2026-01-03T08:00:00Z",
        "e": "2026-01-03T13:00:00Z",
        "d": null,
        "j": null,
        "u": null,
        "t": "playlist"
      },
      {
        "n": "Bé.",
        "s": "2026-01-03T13:00:00Z",
        "e": "2026-01-03T14:00:00Z",
        "d": null,
        "j": null,
        "u": null,
        "t": "monthly"
      },
      {
        "n": "Hadj Sameer",
        "s": "2026-01-03T14:00:00Z",
        "e": "2026-01-03T15:00:00Z",
        "d": null,
        "j": "invite Luc & Robin aka Luckyrobin",
        "u": null,
        "t": "monthly"
      },
      {
        "n": "Mattias Mimoun",
        "s": "2026-01-03T15:00:00Z",
        "e": "2026-01-03T16:00:00Z",
        "d": null,
        "j": "PREMIERES W/ KeiyaA",
        "u": null,
        "t": "biweekly"
      },
      {
        "n": "kIM0 presents POV",
        "s": "2026-01-03T16:00:00Z",
        "e": "2026-01-03T17:00:00Z",
        "d": null,
        "j": "Serial Experiments Lain",
        "u": null,
        "t": "monthly"
      },
      {
        "n": "Bait",
        "s": "2026-01-03T17:00:00Z",
        "e": "2026-01-03T18:00:00Z",
        "d": null,
        "j": "présente Chewlie (100% production mix)",
        "u": null,
        "t": "monthly"
      },
      {
        "n": "Imer6ia",
        "s": "2026-01-03T18:00:00Z",
        "e": "2026-01-03T19:00:00Z",
        "d": null,
        "j": null,
        "u": null,
        "t": "monthly"
      },
      {
        "n": "Playlist France",
        "s": "2026-01-03T19:00:00Z",
        "e": "2026-01-03T20:00:00Z",
        "d": null,
        "j": null,
        "u": null,
        "t": "playlist"
      }
    ],
    "newtown": []
  }
}